<annotation>
	<folder/>
	<filename>image000050.jpg</filename>
	<path>image000050.jpg</path>
	<source>
		<database>Unknown</database>
	</source>
	<size>
		<width>720</width>
		<height>480</height>
		<depth>3</depth>
	</size>
	<segmented>0</segmented>
	<object>
		<name>bear</name>
		<pose>Unspecified</pose>
		<truncated>0</truncated>
		<difficult>0</difficult>
		<bndbox>
			<xmin>329</xmin>
			<ymin>167</ymin>
			<xmax>501</xmax>
			<ymax>449</ymax>
		</bndbox>
		<bbox_source>single_object_tracker</bbox_source>
		<id_number>1</id_number>
		<score>0</score>
		<mask>330.642,326.46299999999997,1; 330.341,326.46299999999997,1; 330.341,326.16200000000003,1; 330.341,325.861,1; 330.04,325.861,1; 330.04,325.56,1; 330.04,325.259,1; 330.04,324.95799999999997,1; 330.04,324.65700000000004,1; 330.04,324.356,1; 330.04,324.055,1; 330.04,323.754,1; 329.739,323.754,1; 330.04,323.453,1; 330.04,323.152,1; 329.739,323.152,1; 329.739,322.851,1; 329.739,322.55,1; 329.739,322.249,1; 329.739,321.948,1; 329.739,321.647,1; 329.739,321.346,1; 329.739,321.04499999999996,1; 329.739,320.744,1; 329.739,320.443,1; 329.739,320.142,1; 330.04,319.841,1; 330.04,319.53999999999996,1; 330.04,319.23900000000003,1; 330.04,318.938,1; 330.04,318.637,1; 330.04,318.336,1; 330.341,318.336,1; 330.341,318.03499999999997,1; 330.341,317.73400000000004,1; 330.642,317.73400000000004,1; 330.642,317.433,1; 330.642,317.132,1; 330.943,316.831,1; 330.943,316.53,1; 330.943,316.22900000000004,1; 331.244,316.22900000000004,1; 331.244,315.928,1; 331.545,315.928,1; 331.545,315.627,1; 331.545,315.326,1; 331.846,315.326,1; 331.846,315.025,1; 331.846,314.724,1; 332.147,314.724,1; 332.147,314.423,1; 332.448,314.122,1; 332.749,313.821,1; 333.05,313.52,1; 333.05,313.219,1; 333.05,312.918,1; 333.05,313.219,1; 333.351,312.918,1; 333.351,312.61699999999996,1; 333.652,312.61699999999996,1; 333.652,312.31600000000003,1; 333.953,312.015,1; 333.953,311.714,1; 334.254,311.714,1; 334.254,311.413,1; 334.555,311.413,1; 334.555,311.11199999999997,1; 334.555,310.81100000000004,1; 334.856,310.81100000000004,1; 334.856,310.51,1; 335.157,310.51,1; 335.157,310.209,1; 335.45799999999997,310.209,1; 335.45799999999997,309.908,1; 335.45799999999997,309.60699999999997,1; 335.759,309.60699999999997,1; 335.759,309.30600000000004,1; 335.759,309.005,1; 336.06,309.005,1; 336.06,308.704,1; 336.361,308.704,1; 336.361,308.403,1; 336.361,308.102,1; 336.662,308.102,1; 336.662,307.801,1; 336.662,307.5,1; 336.963,307.199,1; 336.963,306.898,1; 336.963,306.597,1; 337.264,306.296,1; 337.264,305.995,1; 337.264,305.69399999999996,1; 337.565,305.39300000000003,1; 337.565,305.092,1; 337.565,304.791,1; 337.866,304.49,1; 337.866,304.18899999999996,1; 337.866,303.88800000000003,1; 337.866,303.587,1; 337.866,303.286,1; 338.16700000000003,303.286,1; 338.16700000000003,302.985,1; 338.16700000000003,302.68399999999997,1; 338.16700000000003,302.38300000000004,1; 338.16700000000003,302.082,1; 338.16700000000003,301.781,1; 338.16700000000003,301.48,1; 338.16700000000003,301.179,1; 338.16700000000003,300.878,1; 338.16700000000003,300.577,1; 338.16700000000003,300.276,1; 338.16700000000003,299.975,1; 338.16700000000003,299.674,1; 338.16700000000003,299.373,1; 338.16700000000003,299.072,1; 338.16700000000003,298.77099999999996,1; 338.16700000000003,298.47,1; 338.16700000000003,298.169,1; 338.16700000000003,297.868,1; 338.16700000000003,297.567,1; 338.16700000000003,297.26599999999996,1; 338.16700000000003,296.96500000000003,1; 338.16700000000003,296.664,1; 338.16700000000003,296.363,1; 338.16700000000003,296.062,1; 338.16700000000003,295.76099999999997,1; 338.16700000000003,295.46000000000004,1; 338.16700000000003,295.159,1; 338.16700000000003,294.858,1; 338.16700000000003,294.557,1; 338.16700000000003,294.256,1; 338.16700000000003,293.95500000000004,1; 338.16700000000003,293.654,1; 338.16700000000003,293.353,1; 338.16700000000003,293.052,1; 338.16700000000003,292.751,1; 338.16700000000003,292.45,1; 338.16700000000003,292.149,1; 338.16700000000003,291.848,1; 338.16700000000003,291.547,1; 338.16700000000003,291.246,1; 338.16700000000003,290.945,1; 338.16700000000003,290.644,1; 338.16700000000003,290.34299999999996,1; 338.16700000000003,290.04200000000003,1; 337.866,290.04200000000003,1; 337.866,289.741,1; 337.866,289.44,1; 337.866,289.139,1; 337.866,288.83799999999997,1; 337.866,288.53700000000003,1; 337.565,288.236,1; 337.565,287.935,1; 337.565,287.634,1; 337.565,287.33299999999997,1; 337.565,287.03200000000004,1; 337.565,286.731,1; 337.565,286.43,1; 337.565,286.129,1; 337.565,285.828,1; 337.565,285.527,1; 337.565,285.226,1; 337.565,284.925,1; 337.565,284.624,1; 337.565,284.323,1; 337.565,284.022,1; 337.565,283.721,1; 337.565,283.42,1; 337.565,283.119,1; 337.565,282.818,1; 337.565,282.517,1; 337.565,282.216,1; 337.565,281.915,1; 337.565,281.61400000000003,1; 337.866,280.711,1; 337.866,280.40999999999997,1; 337.866,280.711,1; 337.866,280.40999999999997,1; 337.866,280.109,1; 337.866,279.808,1; 337.866,279.507,1; 337.866,279.206,1; 337.866,278.905,1; 337.866,278.604,1; 337.866,278.303,1; 338.16700000000003,278.303,1; 338.16700000000003,278.002,1; 338.468,277.701,1; 338.468,277.4,1; 338.769,277.4,1; 338.769,277.099,1; 338.769,276.798,1; 339.07,276.798,1; 339.07,276.497,1; 339.371,276.497,1; 339.371,276.196,1; 339.672,276.196,1; 339.973,275.895,1; 340.274,275.594,1; 340.274,275.293,1; 340.575,275.293,1; 340.575,274.992,1; 340.575,274.69100000000003,1; 340.876,274.992,1; 340.876,274.69100000000003,1; 341.177,274.69100000000003,1; 341.177,274.39,1; 341.177,274.089,1; 341.177,273.788,1; 341.177,274.089,1; 341.177,273.788,1; 341.478,273.788,1; 341.478,273.48699999999997,1; 341.478,273.18600000000004,1; 341.478,272.885,1; 341.779,272.885,1; 341.779,272.584,1; 341.779,272.283,1; 341.779,271.98199999999997,1; 341.779,271.681,1; 342.08,271.38,1; 342.08,271.079,1; 342.08,270.778,1; 342.08,270.477,1; 342.381,270.477,1; 342.08,270.477,1; 342.381,270.477,1; 342.08,270.477,1; 342.381,270.176,1; 342.381,269.875,1; 342.381,269.574,1; 342.381,269.273,1; 342.381,268.972,1; 342.682,268.972,1; 342.381,268.671,1; 342.682,268.671,1; 342.682,268.37,1; 342.682,268.069,1; 342.682,267.76800000000003,1; 342.682,267.467,1; 342.983,267.467,1; 342.983,267.166,1; 342.983,266.865,1; 342.983,266.56399999999996,1; 343.284,266.26300000000003,1; 343.284,265.962,1; 343.585,265.661,1; 343.585,265.36,1; 343.585,265.05899999999997,1; 343.886,265.05899999999997,1; 343.886,264.758,1; 343.886,264.457,1; 344.187,264.457,1; 344.187,264.156,1; 344.187,263.855,1; 344.488,263.855,1; 344.488,263.554,1; 344.488,263.253,1; 344.789,263.253,1; 344.789,262.952,1; 345.09,262.651,1; 345.09,262.35,1; 345.391,262.35,1; 345.391,262.049,1; 345.692,261.748,1; 345.993,261.447,1; 345.993,261.146,1; 346.294,261.146,1; 346.294,260.845,1; 346.595,260.845,1; 346.595,260.544,1; 346.595,260.243,1; 346.896,260.243,1; 346.896,259.942,1; 346.896,259.641,1; 347.197,259.641,1; 347.197,259.34000000000003,1; 347.197,259.039,1; 347.498,259.039,1; 347.498,258.738,1; 347.498,258.437,1; 347.498,258.13599999999997,1; 347.799,258.13599999999997,1; 347.799,257.835,1; 347.799,257.534,1; 347.799,257.233,1; 347.799,256.932,1; 348.1,256.932,1; 348.1,256.631,1; 348.1,256.33,1; 348.1,256.029,1; 348.401,255.728,1; 348.401,255.42700000000002,1; 348.401,255.126,1; 348.702,255.126,1; 348.702,254.825,1; 348.702,254.524,1; 349.003,254.524,1; 349.003,254.223,1; 349.003,253.922,1; 349.304,253.922,1; 349.304,253.62099999999998,1; 349.304,253.32,1; 349.605,253.32,1; 349.605,253.019,1; 349.605,252.71800000000002,1; 349.605,252.417,1; 349.906,252.417,1; 349.906,252.11599999999999,1; 349.906,251.815,1; 349.906,251.514,1; 349.906,251.213,1; 349.906,250.912,1; 349.906,250.611,1; 349.906,250.31,1; 349.906,250.00900000000001,1; 349.906,249.708,1; 349.605,249.708,1; 349.605,249.40699999999998,1; 349.605,249.106,1; 349.304,248.805,1; 349.304,248.50400000000002,1; 349.304,248.203,1; 349.003,248.203,1; 349.003,247.902,1; 349.003,247.601,1; 349.003,247.3,1; 349.003,246.999,1; 348.702,246.999,1; 348.702,246.69799999999998,1; 348.702,246.397,1; 348.702,246.096,1; 348.702,245.79500000000002,1; 348.702,245.494,1; 348.702,245.19299999999998,1; 348.702,244.892,1; 348.702,244.591,1; 348.702,244.29000000000002,1; 348.702,243.989,1; 348.702,243.688,1; 348.702,243.387,1; 348.702,243.086,1; 348.702,242.785,1; 348.702,242.48399999999998,1; 348.702,242.183,1; 348.702,241.882,1; 348.702,241.58100000000002,1; 348.702,241.28,1; 348.702,240.97899999999998,1; 348.702,240.678,1; 348.702,240.377,1; 348.702,240.076,1; 348.702,239.775,1; 348.702,239.474,1; 348.702,239.173,1; 348.702,238.872,1; 348.702,238.571,1; 349.003,238.571,1; 349.003,238.26999999999998,1; 349.003,237.969,1; 349.304,237.969,1; 349.304,237.668,1; 349.605,237.668,1; 349.605,237.36700000000002,1; 349.906,237.36700000000002,1; 349.605,237.36700000000002,1; 349.906,237.36700000000002,1; 349.906,237.066,1; 349.906,236.765,1; 349.906,237.066,1; 349.906,236.765,1; 350.207,236.765,1; 350.207,236.464,1; 350.207,236.163,1; 350.207,235.862,1; 350.207,235.561,1; 350.207,235.26,1; 350.207,234.959,1; 350.207,234.65800000000002,1; 350.207,234.357,1; 350.207,234.05599999999998,1; 350.207,233.755,1; 350.207,233.454,1; 350.207,233.15300000000002,1; 350.207,232.852,1; 350.207,232.551,1; 350.207,232.25,1; 350.207,231.949,1; 350.207,231.648,1; 350.207,231.34699999999998,1; 350.207,231.046,1; 350.508,231.046,1; 350.508,230.745,1; 350.508,230.44400000000002,1; 350.508,230.143,1; 350.508,229.84199999999998,1; 350.508,229.541,1; 350.508,229.24,1; 350.80899999999997,229.24,1; 350.80899999999997,228.939,1; 350.508,228.939,1; 350.80899999999997,228.638,1; 350.80899999999997,228.337,1; 350.80899999999997,228.036,1; 350.80899999999997,227.735,1; 350.80899999999997,227.434,1; 350.80899999999997,227.13299999999998,1; 351.11,226.832,1; 351.11,226.531,1; 351.11,226.23000000000002,1; 351.11,225.929,1; 351.11,225.628,1; 351.11,225.327,1; 351.11,225.026,1; 351.11,224.725,1; 351.11,224.424,1; 351.411,224.424,1; 351.411,224.123,1; 351.411,223.822,1; 351.411,223.52100000000002,1; 351.411,223.22,1; 351.712,222.91899999999998,1; 351.712,222.618,1; 351.712,222.317,1; 351.712,222.01600000000002,1; 351.712,221.715,1; 352.013,221.715,1; 352.013,221.414,1; 352.013,221.113,1; 352.013,220.812,1; 352.013,220.511,1; 352.314,220.511,1; 352.013,220.511,1; 352.314,220.511,1; 352.314,220.21,1; 352.314,219.909,1; 352.314,219.608,1; 352.615,219.608,1; 352.615,219.30700000000002,1; 352.615,219.006,1; 352.916,219.006,1; 352.916,218.70499999999998,1; 352.916,218.404,1; 353.217,218.404,1; 353.217,218.103,1; 353.217,217.802,1; 353.217,217.501,1; 353.51800000000003,217.501,1; 353.217,217.501,1; 353.51800000000003,217.2,1; 353.51800000000003,216.899,1; 353.51800000000003,216.598,1; 353.819,216.598,1; 353.819,216.297,1; 353.819,215.996,1; 354.12,215.996,1; 354.12,215.695,1; 354.421,215.394,1; 354.421,215.09300000000002,1; 354.421,214.792,1; 354.722,214.792,1; 354.722,214.49099999999999,1; 354.722,214.19,1; 355.023,214.19,1; 354.722,214.19,1; 355.023,214.19,1; 355.023,213.889,1; 355.324,213.889,1; 355.625,213.889,1; 355.926,213.889,1; 356.227,213.889,1; 356.528,213.889,1; 356.829,213.889,1; 357.13,213.889,1; 357.431,213.889,1; 357.73199999999997,213.889,1; 358.033,213.889,1; 358.334,213.889,1; 358.635,213.889,1; 358.936,213.889,1; 359.237,213.889,1; 359.538,213.889,1; 359.839,213.889,1; 360.14,213.889,1; 360.44100000000003,213.889,1; 360.742,213.889,1; 361.043,213.889,1; 361.344,213.889,1; 361.645,213.889,1; 361.946,213.889,1; 362.247,213.889,1; 362.548,213.889,1; 362.849,213.889,1; 362.849,214.19,1; 363.15,214.19,1; 363.451,214.49099999999999,1; 363.752,214.49099999999999,1; 364.053,214.792,1; 364.354,215.09300000000002,1; 364.655,215.394,1; 364.956,215.394,1; 364.956,215.695,1; 364.956,215.996,1; 365.257,215.996,1; 365.257,216.297,1; 365.558,216.598,1; 365.558,216.899,1; 365.558,217.2,1; 365.558,217.501,1; 365.859,217.501,1; 365.859,217.802,1; 365.859,218.103,1; 365.859,218.404,1; 366.15999999999997,218.404,1; 366.15999999999997,218.70499999999998,1; 366.15999999999997,219.006,1; 366.15999999999997,219.30700000000002,1; 366.461,219.30700000000002,1; 366.461,219.608,1; 366.15999999999997,219.608,1; 366.461,219.909,1; 366.461,220.21,1; 366.461,220.511,1; 366.461,220.812,1; 366.461,221.113,1; 366.762,221.113,1; 366.762,221.414,1; 366.762,221.715,1; 367.063,221.715,1; 367.063,222.01600000000002,1; 367.063,222.317,1; 367.063,222.618,1; 367.063,222.91899999999998,1; 367.364,223.22,1; 367.364,223.52100000000002,1; 367.364,223.822,1; 367.364,224.123,1; 367.665,224.123,1; 367.665,224.424,1; 367.665,224.725,1; 367.665,225.026,1; 367.665,225.327,1; 367.665,225.628,1; 367.665,225.929,1; 367.665,226.23000000000002,1; 367.966,226.23000000000002,1; 367.966,226.531,1; 367.966,226.832,1; 367.966,227.13299999999998,1; 367.966,227.434,1; 367.966,227.735,1; 367.966,228.036,1; 367.966,228.337,1; 367.966,228.638,1; 367.966,228.939,1; 367.966,229.24,1; 367.966,229.541,1; 367.966,229.84199999999998,1; 367.966,230.143,1; 367.966,230.44400000000002,1; 368.267,230.44400000000002,1; 368.267,230.745,1; 368.267,231.046,1; 368.267,231.34699999999998,1; 368.267,231.648,1; 368.568,231.949,1; 368.568,232.25,1; 368.568,232.551,1; 368.568,232.852,1; 368.568,233.15300000000002,1; 368.568,233.454,1; 368.568,233.755,1; 368.568,234.05599999999998,1; 368.568,234.357,1; 368.568,234.65800000000002,1; 368.568,234.959,1; 368.568,235.26,1; 368.568,235.561,1; 368.568,235.862,1; 368.869,235.862,1; 368.568,235.862,1; 368.568,236.163,1; 368.869,236.163,1; 368.568,236.464,1; 368.568,236.765,1; 368.568,237.066,1; 369.17,238.571,1; 369.17,238.872,1; 369.17,239.173,1; 369.17,239.474,1; 369.17,239.775,1; 369.17,240.076,1; 369.17,240.377,1; 369.17,240.678,1; 369.471,240.678,1; 369.772,240.678,1; 370.073,240.678,1; 370.374,240.678,1; 370.675,240.678,1; 370.976,240.678,1; 371.277,240.678,1; 371.578,240.678,1; 371.879,240.678,1; 371.879,240.678,1; 372.18,240.678,1; 372.481,240.678,1; 372.481,240.377,1; 372.782,240.377,1; 372.782,240.076,1; 372.782,239.775,1; 373.08299999999997,239.775,1; 373.08299999999997,239.474,1; 373.384,239.173,1; 373.384,238.872,1; 373.685,238.571,1; 373.685,238.26999999999998,1; 373.986,238.26999999999998,1; 373.986,237.969,1; 373.986,237.668,1; 374.287,237.668,1; 374.287,237.36700000000002,1; 374.287,237.066,1; 374.287,236.765,1; 374.588,236.765,1; 374.588,236.464,1; 374.588,236.163,1; 374.588,235.862,1; 374.889,235.862,1; 374.889,235.561,1; 375.19,235.26,1; 375.19,234.959,1; 375.19,234.65800000000002,1; 375.491,234.65800000000002,1; 375.491,234.357,1; 375.491,234.05599999999998,1; 375.79200000000003,234.05599999999998,1; 375.79200000000003,233.755,1; 376.093,233.755,1; 376.093,233.454,1; 376.093,233.15300000000002,1; 376.394,232.852,1; 376.394,232.551,1; 376.695,232.25,1; 376.695,231.949,1; 376.996,231.949,1; 376.996,231.648,1; 376.996,231.34699999999998,1; 377.297,231.34699999999998,1; 377.297,231.046,1; 377.598,230.745,1; 377.598,230.44400000000002,1; 377.598,230.143,1; 377.899,230.143,1; 377.899,229.84199999999998,1; 378.2,229.541,1; 378.2,229.24,1; 378.501,228.939,1; 378.501,228.638,1; 378.802,228.638,1; 378.802,228.337,1; 378.802,228.036,1; 379.103,228.036,1; 379.103,227.735,1; 379.404,227.434,1; 379.404,227.13299999999998,1; 379.705,226.832,1; 379.705,226.531,1; 380.006,226.23000000000002,1; 380.006,225.929,1; 380.006,225.628,1; 380.307,225.628,1; 380.307,225.327,1; 380.307,225.026,1; 380.608,225.026,1; 380.608,224.725,1; 380.608,224.424,1; 380.909,224.123,1; 380.909,223.822,1; 381.21,223.822,1; 381.21,223.52100000000002,1; 381.21,223.22,1; 381.511,223.22,1; 381.511,222.91899999999998,1; 381.511,222.618,1; 381.812,222.317,1; 382.113,222.317,1; 382.113,222.01600000000002,1; 382.113,221.715,1; 382.414,221.715,1; 382.414,221.414,1; 382.71500000000003,221.113,1; 382.71500000000003,220.812,1; 383.016,220.511,1; 383.317,220.21,1; 383.618,219.909,1; 383.618,219.608,1; 383.919,219.30700000000002,1; 384.22,219.006,1; 384.22,218.70499999999998,1; 384.521,218.404,1; 384.822,218.404,1; 384.822,218.103,1; 385.123,217.802,1; 385.424,217.501,1; 385.424,217.2,1; 385.725,217.2,1; 385.725,216.899,1; 385.725,216.598,1; 386.026,216.598,1; 386.026,216.297,1; 386.327,216.297,1; 386.327,215.996,1; 386.628,215.695,1; 386.929,215.394,1; 387.23,215.09300000000002,1; 387.23,214.792,1; 387.531,214.792,1; 387.531,214.49099999999999,1; 387.832,214.19,1; 388.133,214.19,1; 388.133,213.889,1; 388.43399999999997,213.588,1; 388.735,213.287,1; 388.735,212.986,1; 389.036,212.685,1; 389.337,212.38400000000001,1; 389.63800000000003,212.083,1; 389.93899999999996,212.083,1; 389.63800000000003,211.78199999999998,1; 389.93899999999996,211.78199999999998,1; 390.24,211.481,1; 390.541,211.481,1; 390.842,211.481,1; 391.14300000000003,211.481,1; 391.444,211.481,1; 391.14300000000003,211.481,1; 391.444,211.481,1; 391.745,211.481,1; 391.745,211.18,1; 392.046,211.18,1; 392.347,211.18,1; 392.347,210.879,1; 392.648,210.879,1; 392.648,210.578,1; 392.949,210.578,1; 392.949,210.277,1; 393.25,209.976,1; 393.551,209.976,1; 393.551,209.675,1; 393.551,209.374,1; 393.852,209.374,1; 393.551,209.374,1; 393.852,209.374,1; 393.852,209.073,1; 394.153,209.073,1; 394.153,208.772,1; 394.454,208.471,1; 394.454,208.17000000000002,1; 394.755,208.17000000000002,1; 394.755,207.869,1; 394.755,207.56799999999998,1; 395.056,207.56799999999998,1; 395.056,207.267,1; 395.056,206.966,1; 395.35699999999997,206.966,1; 395.35699999999997,206.665,1; 395.658,206.364,1; 395.959,206.063,1; 395.959,205.762,1; 396.26,205.461,1; 396.26,205.16,1; 396.56100000000004,205.16,1; 396.56100000000004,204.859,1; 396.56100000000004,204.558,1; 396.86199999999997,204.558,1; 396.86199999999997,204.257,1; 397.163,204.257,1; 397.163,203.95600000000002,1; 397.163,203.655,1; 397.464,203.35399999999998,1; 397.464,203.053,1; 397.765,202.752,1; 397.765,202.451,1; 398.06600000000003,202.15,1; 398.06600000000003,201.849,1; 398.06600000000003,201.548,1; 398.367,201.247,1; 398.367,200.946,1; 398.367,200.645,1; 398.668,200.344,1; 398.668,200.043,1; 398.969,199.742,1; 398.969,199.441,1; 398.969,199.14,1; 398.969,198.839,1; 398.969,198.538,1; 399.27,198.237,1; 399.27,197.936,1; 399.571,197.635,1; 399.571,197.334,1; 399.571,197.03300000000002,1; 399.872,196.732,1; 399.872,196.43099999999998,1; 399.872,196.13,1; 399.872,195.829,1; 400.173,195.829,1; 400.173,195.528,1; 400.173,195.227,1; 400.474,195.227,1; 400.474,194.926,1; 400.474,194.625,1; 400.474,194.324,1; 400.775,194.324,1; 400.775,194.023,1; 400.775,193.722,1; 401.076,193.421,1; 401.076,193.12,1; 401.377,192.81900000000002,1; 401.377,192.518,1; 401.678,192.21699999999998,1; 401.678,191.916,1; 401.979,191.615,1; 402.28,191.314,1; 402.28,191.013,1; 402.28,190.712,1; 402.581,190.712,1; 402.581,190.411,1; 402.882,190.11,1; 402.882,189.809,1; 403.183,189.809,1; 403.183,189.508,1; 403.484,189.207,1; 403.484,188.906,1; 403.78499999999997,188.605,1; 403.78499999999997,188.304,1; 403.78499999999997,188.003,1; 404.086,188.003,1; 404.086,187.702,1; 404.387,187.401,1; 404.387,187.1,1; 404.688,186.799,1; 404.688,186.498,1; 404.98900000000003,186.498,1; 404.98900000000003,186.197,1; 404.98900000000003,185.89600000000002,1; 405.29,185.595,1; 405.29,185.294,1; 405.591,185.294,1; 405.591,184.993,1; 405.892,184.993,1; 405.892,184.692,1; 406.193,184.391,1; 406.193,184.09,1; 406.494,183.789,1; 406.494,183.488,1; 406.795,183.488,1; 407.096,183.187,1; 407.397,182.886,1; 407.698,182.886,1; 407.698,182.585,1; 407.999,182.585,1; 407.999,182.284,1; 408.3,181.983,1; 408.601,181.983,1; 408.902,181.682,1; 409.203,181.682,1; 409.203,181.381,1; 409.504,181.381,1; 409.504,181.07999999999998,1; 409.805,181.07999999999998,1; 410.106,180.779,1; 410.407,180.779,1; 410.407,180.478,1; 410.70799999999997,180.478,1; 411.009,180.478,1; 411.31,180.177,1; 411.31,180.478,1; 411.31,180.177,1; 411.611,180.177,1; 411.91200000000003,180.177,1; 412.21299999999997,180.177,1; 412.514,180.177,1; 412.815,179.876,1; 412.815,180.177,1; 413.116,180.177,1; 413.41700000000003,180.177,1; 413.718,180.177,1; 413.718,179.876,1; 414.019,179.876,1; 414.32,179.876,1; 414.32,179.575,1; 414.621,179.575,1; 414.922,179.575,1; 414.922,179.274,1; 415.223,179.274,1; 415.223,178.973,1; 415.223,179.274,1; 415.524,179.274,1; 415.223,179.274,1; 415.223,178.973,1; 415.524,178.973,1; 415.825,178.973,1; 416.126,178.672,1; 416.427,178.672,1; 416.427,178.371,1; 416.728,178.371,1; 417.029,178.07,1; 417.33,177.769,1; 417.33,177.468,1; 417.631,177.167,1; 417.932,176.86599999999999,1; 418.233,176.565,1; 418.534,176.264,1; 418.835,175.963,1; 419.13599999999997,175.662,1; 419.13599999999997,175.361,1; 419.437,175.06,1; 419.738,175.06,1; 419.738,174.75900000000001,1; 420.039,174.458,1; 420.34000000000003,174.157,1; 420.641,173.856,1; 420.942,173.555,1; 421.243,173.254,1; 421.544,172.953,1; 421.845,172.652,1; 422.146,172.652,1; 422.146,172.351,1; 422.447,172.05,1; 422.748,172.05,1; 422.748,171.749,1; 423.049,171.749,1; 423.35,171.448,1; 423.35,171.147,1; 423.651,171.147,1; 423.952,170.846,1; 423.952,170.545,1; 424.253,170.244,1; 424.554,170.244,1; 424.855,169.943,1; 425.156,169.642,1; 425.457,169.642,1; 425.758,169.341,1; 426.05899999999997,169.04,1; 426.05899999999997,168.739,1; 426.36,168.739,1; 426.661,168.739,1; 426.661,168.438,1; 426.962,168.438,1; 426.962,168.137,1; 427.26300000000003,168.137,1; 427.56399999999996,167.836,1; 427.865,167.836,1; 428.166,167.535,1; 428.467,167.535,1; 428.467,167.234,1; 428.76800000000003,167.234,1; 429.069,167.234,1; 429.37,167.234,1; 429.671,167.234,1; 429.972,167.234,1; 430.273,167.234,1; 430.574,167.234,1; 430.875,167.234,1; 431.176,167.234,1; 431.176,167.535,1; 431.477,167.535,1; 431.778,167.836,1; 432.079,167.836,1; 432.38,168.137,1; 432.681,168.137,1; 432.98199999999997,168.438,1; 433.283,168.438,1; 433.584,168.438,1; 433.584,168.739,1; 433.885,168.739,1; 433.885,169.04,1; 434.18600000000004,169.04,1; 434.18600000000004,169.341,1; 434.48699999999997,169.341,1; 434.48699999999997,169.642,1; 434.788,169.642,1; 434.788,169.943,1; 435.089,169.943,1; 435.089,170.244,1; 435.39,170.244,1; 435.69100000000003,170.545,1; 435.69100000000003,170.846,1; 435.992,170.846,1; 435.992,171.147,1; 436.293,171.147,1; 436.594,171.448,1; 436.594,171.749,1; 436.895,171.749,1; 436.895,172.05,1; 437.196,172.05,1; 437.196,172.351,1; 437.497,172.351,1; 437.497,172.652,1; 437.798,172.652,1; 438.099,172.953,1; 438.4,173.254,1; 438.701,173.555,1; 438.701,173.856,1; 439.002,173.856,1; 439.002,174.157,1; 439.303,174.157,1; 439.303,174.458,1; 439.604,174.458,1; 439.905,174.75900000000001,1; 439.905,175.06,1; 440.206,175.06,1; 440.206,175.361,1; 440.507,175.361,1; 440.507,175.662,1; 440.808,175.662,1; 441.109,175.662,1; 441.109,175.963,1; 441.40999999999997,175.963,1; 441.40999999999997,176.264,1; 441.711,176.264,1; 442.012,176.264,1; 442.012,176.565,1; 442.313,176.565,1; 442.61400000000003,176.86599999999999,1; 442.61400000000003,177.167,1; 442.915,177.167,1; 442.915,177.468,1; 443.216,177.468,1; 443.216,177.769,1; 443.517,177.769,1; 443.818,177.769,1; 443.818,178.07,1; 444.119,178.07,1; 444.42,178.07,1; 445.022,178.07,1; 445.022,178.371,1; 445.323,178.371,1; 445.624,178.672,1; 445.925,178.672,1; 446.226,178.672,1; 446.527,178.973,1; 446.828,179.274,1; 447.129,179.274,1; 447.129,179.575,1; 447.129,179.876,1; 447.129,180.177,1; 447.43,180.478,1; 447.43,180.779,1; 447.731,180.779,1; 447.731,181.07999999999998,1; 447.731,181.381,1; 447.731,181.682,1; 448.03200000000004,181.682,1; 448.03200000000004,181.983,1; 448.03200000000004,182.284,1; 447.731,182.585,1; 448.03200000000004,182.585,1; 448.03200000000004,182.886,1; 448.03200000000004,183.187,1; 448.03200000000004,183.488,1; 448.03200000000004,183.789,1; 448.03200000000004,184.09,1; 448.03200000000004,184.391,1; 448.33299999999997,184.391,1; 448.33299999999997,184.692,1; 448.33299999999997,184.993,1; 448.33299999999997,185.294,1; 448.634,185.595,1; 448.634,185.89600000000002,1; 448.634,186.197,1; 448.634,186.498,1; 448.935,186.498,1; 448.935,186.799,1; 448.935,187.1,1; 449.236,186.799,1; 449.236,187.1,1; 449.53700000000003,187.1,1; 449.83799999999997,187.401,1; 450.139,187.401,1; 450.44,187.702,1; 450.741,187.702,1; 450.741,188.003,1; 451.04200000000003,188.003,1; 451.34299999999996,188.003,1; 451.34299999999996,188.304,1; 451.644,188.304,1; 451.945,188.304,1; 451.945,188.605,1; 452.246,188.605,1; 452.547,188.906,1; 452.848,189.207,1; 453.149,189.207,1; 453.45,189.207,1; 453.751,189.508,1; 454.052,189.508,1; 454.353,189.508,1; 454.353,189.809,1; 454.654,189.809,1; 454.95500000000004,189.809,1; 454.95500000000004,190.11,1; 455.256,190.11,1; 455.557,190.11,1; 455.557,190.411,1; 455.858,190.411,1; 456.159,190.712,1; 456.46000000000004,190.712,1; 456.76099999999997,190.712,1; 456.76099999999997,191.013,1; 457.062,191.013,1; 457.363,191.013,1; 457.664,191.013,1; 457.664,191.314,1; 457.96500000000003,191.314,1; 458.26599999999996,191.615,1; 458.567,191.615,1; 458.868,191.916,1; 459.169,191.916,1; 459.169,192.21699999999998,1; 459.47,192.21699999999998,1; 459.77099999999996,192.518,1; 460.072,192.518,1; 460.373,192.81900000000002,1; 460.674,192.81900000000002,1; 460.975,192.81900000000002,1; 461.276,193.12,1; 461.577,193.421,1; 461.878,193.421,1; 461.878,193.722,1; 462.179,193.722,1; 462.48,193.722,1; 462.781,194.023,1; 463.082,194.023,1; 463.38300000000004,194.324,1; 463.68399999999997,194.324,1; 463.985,194.324,1; 464.286,194.324,1; 464.587,194.625,1; 464.88800000000003,194.625,1; 465.18899999999996,194.625,1; 465.49,194.625,1; 465.791,194.926,1; 466.092,194.926,1; 466.39300000000003,194.926,1; 466.39300000000003,195.227,1; 466.69399999999996,195.227,1; 466.69399999999996,195.528,1; 466.995,195.528,1; 466.995,195.829,1; 466.995,196.13,1; 467.296,196.13,1; 467.296,196.43099999999998,1; 467.296,196.732,1; 467.597,197.03300000000002,1; 467.597,197.334,1; 467.898,197.334,1; 467.898,197.635,1; 468.199,197.936,1; 468.5,198.237,1; 468.801,198.538,1; 469.102,198.538,1; 469.102,198.839,1; 469.403,199.14,1; 469.704,199.14,1; 469.704,199.441,1; 470.005,199.441,1; 470.005,199.742,1; 470.30600000000004,199.742,1; 470.30600000000004,200.043,1; 470.60699999999997,200.344,1; 470.908,200.645,1; 471.209,200.946,1; 471.51,200.946,1; 471.51,201.247,1; 471.81100000000004,201.247,1; 471.81100000000004,201.548,1; 472.11199999999997,201.548,1; 472.413,201.849,1; 472.714,202.15,1; 473.015,202.15,1; 473.015,202.451,1; 473.31600000000003,202.451,1; 473.31600000000003,202.752,1; 473.61699999999996,202.752,1; 473.61699999999996,203.053,1; 473.918,203.35399999999998,1; 473.918,203.655,1; 474.219,203.655,1; 474.52,203.95600000000002,1; 474.821,204.257,1; 474.821,204.558,1; 475.122,204.859,1; 475.423,205.16,1; 475.423,205.461,1; 475.724,205.461,1; 475.724,205.762,1; 476.025,205.762,1; 476.025,206.063,1; 476.326,206.063,1; 476.326,206.364,1; 476.326,206.665,1; 476.627,206.665,1; 476.627,206.966,1; 476.627,207.267,1; 476.928,207.56799999999998,1; 477.22900000000004,207.869,1; 477.22900000000004,208.17000000000002,1; 477.53,208.17000000000002,1; 477.53,208.471,1; 477.53,208.772,1; 477.831,208.772,1; 477.831,209.073,1; 478.132,209.374,1; 478.132,209.675,1; 478.433,209.976,1; 478.433,210.277,1; 478.73400000000004,210.277,1; 478.73400000000004,210.578,1; 478.73400000000004,210.879,1; 479.03499999999997,210.879,1; 479.03499999999997,211.18,1; 479.03499999999997,211.481,1; 479.336,211.481,1; 479.336,211.78199999999998,1; 479.637,211.78199999999998,1; 479.637,212.083,1; 479.938,212.38400000000001,1; 480.23900000000003,212.685,1; 480.23900000000003,212.986,1; 480.53999999999996,212.986,1; 480.53999999999996,213.287,1; 480.841,213.588,1; 480.841,213.889,1; 481.142,213.889,1; 481.142,214.19,1; 481.142,214.49099999999999,1; 481.443,214.49099999999999,1; 481.443,214.792,1; 481.744,214.792,1; 481.744,215.09300000000002,1; 482.04499999999996,215.394,1; 482.346,215.695,1; 482.346,215.996,1; 482.647,216.297,1; 482.647,216.598,1; 482.948,216.598,1; 482.948,216.899,1; 483.249,216.899,1; 483.249,217.2,1; 483.249,217.501,1; 483.55,217.501,1; 483.55,217.802,1; 483.851,217.802,1; 483.851,218.103,1; 484.152,218.404,1; 484.152,218.70499999999998,1; 484.453,218.70499999999998,1; 484.754,219.006,1; 484.754,219.30700000000002,1; 485.055,219.30700000000002,1; 485.055,219.608,1; 485.356,219.909,1; 485.356,220.21,1; 485.65700000000004,220.21,1; 485.65700000000004,220.511,1; 485.95799999999997,220.812,1; 485.95799999999997,221.113,1; 485.95799999999997,221.414,1; 485.95799999999997,221.715,1; 485.95799999999997,222.01600000000002,1; 485.95799999999997,222.317,1; 486.259,222.618,1; 486.259,222.91899999999998,1; 486.56,223.22,1; 486.861,223.52100000000002,1; 486.861,223.822,1; 487.16200000000003,224.123,1; 487.46299999999997,224.424,1; 487.46299999999997,224.725,1; 487.46299999999997,225.026,1; 487.46299999999997,225.327,1; 487.764,225.327,1; 487.764,225.628,1; 487.764,225.929,1; 488.065,225.929,1; 488.065,226.23000000000002,1; 488.065,226.531,1; 488.065,226.832,1; 488.366,226.832,1; 488.065,226.832,1; 488.366,226.832,1; 488.366,227.13299999999998,1; 488.366,227.434,1; 488.66700000000003,227.735,1; 488.66700000000003,228.036,1; 488.96799999999996,228.337,1; 488.96799999999996,228.638,1; 489.269,228.638,1; 489.269,228.939,1; 489.57,228.939,1; 489.57,229.24,1; 489.871,229.24,1; 489.871,229.541,1; 489.871,229.84199999999998,1; 489.871,230.143,1; 490.172,230.143,1; 490.172,230.44400000000002,1; 490.172,230.745,1; 490.473,230.745,1; 490.473,231.046,1; 490.473,231.34699999999998,1; 490.774,231.34699999999998,1; 490.774,231.648,1; 491.075,231.949,1; 491.075,232.25,1; 491.075,232.551,1; 491.376,232.852,1; 491.376,233.15300000000002,1; 491.677,233.454,1; 491.677,233.755,1; 491.978,233.755,1; 491.978,234.05599999999998,1; 491.978,234.357,1; 491.978,234.65800000000002,1; 491.978,234.959,1; 491.978,235.26,1; 491.978,235.561,1; 492.279,235.862,1; 492.279,236.163,1; 492.279,236.464,1; 492.279,236.765,1; 492.58000000000004,237.066,1; 492.58000000000004,237.668,1; 492.881,237.668,1; 492.881,237.969,1; 492.881,238.26999999999998,1; 492.881,238.571,1; 493.182,238.872,1; 493.182,239.173,1; 493.182,239.474,1; 493.182,239.775,1; 493.182,240.076,1; 493.182,240.377,1; 493.182,240.678,1; 493.483,240.97899999999998,1; 493.483,241.28,1; 493.483,241.58100000000002,1; 493.483,241.882,1; 493.784,242.183,1; 493.784,242.48399999999998,1; 493.784,242.785,1; 493.784,243.086,1; 494.08500000000004,243.086,1; 494.08500000000004,243.387,1; 494.08500000000004,243.688,1; 494.08500000000004,243.989,1; 494.38599999999997,244.29000000000002,1; 494.38599999999997,244.591,1; 494.38599999999997,244.892,1; 494.38599999999997,245.19299999999998,1; 494.38599999999997,245.494,1; 494.38599999999997,245.79500000000002,1; 494.38599999999997,246.096,1; 494.687,246.096,1; 494.687,246.397,1; 494.687,246.69799999999998,1; 494.687,246.999,1; 494.687,247.3,1; 494.687,247.601,1; 494.988,247.902,1; 494.988,248.203,1; 494.988,248.50400000000002,1; 494.988,248.805,1; 495.289,248.805,1; 495.289,249.106,1; 495.289,249.40699999999998,1; 495.289,249.708,1; 495.289,250.00900000000001,1; 495.59000000000003,250.00900000000001,1; 495.59000000000003,250.31,1; 495.59000000000003,250.611,1; 495.59000000000003,250.912,1; 495.59000000000003,251.213,1; 495.89099999999996,251.514,1; 495.89099999999996,251.815,1; 495.89099999999996,252.11599999999999,1; 496.192,252.11599999999999,1; 496.192,252.417,1; 496.192,252.71800000000002,1; 496.192,253.019,1; 496.493,253.019,1; 496.192,253.019,1; 496.192,253.32,1; 496.493,253.32,1; 496.493,253.62099999999998,1; 496.493,253.922,1; 496.493,254.223,1; 496.794,254.223,1; 496.794,254.524,1; 496.794,254.825,1; 496.794,255.126,1; 496.794,255.42700000000002,1; 497.095,255.42700000000002,1; 497.095,255.728,1; 497.095,256.029,1; 497.39599999999996,256.33,1; 497.39599999999996,256.631,1; 497.39599999999996,256.932,1; 497.39599999999996,257.233,1; 497.697,257.534,1; 497.697,257.835,1; 497.998,258.13599999999997,1; 497.998,258.437,1; 498.299,258.437,1; 498.299,258.738,1; 498.299,259.039,1; 498.6,259.039,1; 498.6,259.34000000000003,1; 498.901,259.34000000000003,1; 498.901,259.641,1; 498.901,259.942,1; 499.202,260.243,1; 499.202,260.544,1; 499.503,260.544,1; 499.503,260.845,1; 499.503,261.146,1; 499.804,261.146,1; 499.804,261.447,1; 500.105,261.748,1; 500.105,262.049,1; 500.105,262.35,1; 500.105,262.651,1; 500.105,262.952,1; 500.105,263.253,1; 500.105,263.554,1; 500.105,263.855,1; 500.105,264.156,1; 500.105,264.457,1; 500.105,264.758,1; 500.105,265.05899999999997,1; 500.105,265.36,1; 500.105,265.661,1; 500.105,265.962,1; 500.105,266.26300000000003,1; 500.105,266.56399999999996,1; 500.105,266.865,1; 500.105,267.467,1; 500.105,268.069,1; 500.105,268.37,1; 500.406,268.671,1; 500.406,268.972,1; 500.406,269.273,1; 500.406,269.574,1; 500.406,269.875,1; 500.406,270.176,1; 500.406,270.477,1; 500.406,270.778,1; 500.406,271.079,1; 500.406,271.38,1; 500.406,271.681,1; 500.406,271.98199999999997,1; 500.406,272.283,1; 500.707,272.584,1; 500.707,272.885,1; 500.707,273.18600000000004,1; 500.707,273.48699999999997,1; 500.707,273.788,1; 500.707,274.089,1; 500.707,274.39,1; 501.00800000000004,274.39,1; 501.00800000000004,274.69100000000003,1; 500.707,274.69100000000003,1; 500.707,274.992,1; 500.707,275.293,1; 500.707,275.594,1; 500.707,275.895,1; 500.707,276.196,1; 500.707,276.497,1; 500.707,276.798,1; 500.707,277.099,1; 500.707,277.4,1; 500.707,277.701,1; 500.707,278.002,1; 500.707,278.303,1; 501.00800000000004,278.905,1; 501.00800000000004,279.206,1; 501.00800000000004,279.507,1; 501.00800000000004,279.808,1; 501.00800000000004,280.40999999999997,1; 501.00800000000004,280.711,1; 501.00800000000004,281.012,1; 501.00800000000004,281.313,1; 501.00800000000004,281.61400000000003,1; 501.00800000000004,281.915,1; 501.30899999999997,282.216,1; 501.00800000000004,282.216,1; 501.30899999999997,282.216,1; 501.30899999999997,282.517,1; 501.00800000000004,282.517,1; 501.00800000000004,282.818,1; 501.00800000000004,283.119,1; 501.00800000000004,283.42,1; 501.00800000000004,283.721,1; 501.00800000000004,284.022,1; 501.00800000000004,284.323,1; 501.00800000000004,284.624,1; 501.00800000000004,284.925,1; 501.00800000000004,285.226,1; 501.00800000000004,285.527,1; 501.00800000000004,285.828,1; 501.00800000000004,286.129,1; 501.00800000000004,286.43,1; 501.00800000000004,286.731,1; 501.00800000000004,287.03200000000004,1; 501.00800000000004,287.33299999999997,1; 501.00800000000004,287.634,1; 501.00800000000004,287.935,1; 501.00800000000004,288.236,1; 501.00800000000004,288.53700000000003,1; 501.00800000000004,288.83799999999997,1; 500.707,288.83799999999997,1; 500.707,289.139,1; 500.707,289.44,1; 500.406,289.741,1; 500.406,290.04200000000003,1; 500.406,290.34299999999996,1; 500.406,290.644,1; 500.105,290.644,1; 500.105,290.945,1; 500.105,291.246,1; 499.804,291.547,1; 499.804,291.848,1; 499.804,292.149,1; 499.804,292.45,1; 499.804,292.751,1; 499.503,293.052,1; 499.503,293.353,1; 499.503,293.654,1; 499.503,293.95500000000004,1; 499.202,294.256,1; 499.202,294.557,1; 499.202,294.858,1; 499.202,295.159,1; 498.901,295.159,1; 498.901,295.46000000000004,1; 498.901,295.76099999999997,1; 498.901,296.062,1; 498.6,296.062,1; 498.6,296.363,1; 498.6,296.664,1; 498.299,296.664,1; 498.299,296.96500000000003,1; 498.299,297.26599999999996,1; 497.998,297.567,1; 497.998,297.868,1; 497.998,298.169,1; 497.697,298.169,1; 497.697,298.47,1; 497.39599999999996,298.77099999999996,1; 497.39599999999996,299.072,1; 497.39599999999996,299.373,1; 497.39599999999996,299.674,1; 497.39599999999996,299.975,1; 497.095,299.975,1; 497.095,300.276,1; 497.095,300.577,1; 497.095,300.878,1; 497.095,301.179,1; 497.095,301.48,1; 497.095,301.781,1; 497.095,301.48,1; 497.095,301.781,1; 497.095,302.082,1; 497.095,302.38300000000004,1; 497.095,302.68399999999997,1; 497.095,302.985,1; 496.794,302.985,1; 496.794,303.286,1; 496.794,303.587,1; 496.493,303.587,1; 496.493,303.88800000000003,1; 496.493,304.18899999999996,1; 496.192,304.49,1; 496.192,304.791,1; 496.192,305.092,1; 495.89099999999996,305.092,1; 495.89099999999996,305.39300000000003,1; 495.89099999999996,305.69399999999996,1; 495.89099999999996,305.995,1; 495.89099999999996,306.296,1; 495.89099999999996,306.597,1; 495.89099999999996,306.898,1; 495.59000000000003,307.199,1; 495.89099999999996,307.5,1; 495.89099999999996,307.801,1; 495.59000000000003,308.102,1; 495.59000000000003,308.403,1; 495.89099999999996,308.704,1; 495.59000000000003,309.005,1; 495.59000000000003,309.30600000000004,1; 495.59000000000003,309.60699999999997,1; 495.59000000000003,309.908,1; 495.59000000000003,310.209,1; 495.59000000000003,310.51,1; 495.59000000000003,310.81100000000004,1; 495.59000000000003,311.11199999999997,1; 495.59000000000003,311.413,1; 495.59000000000003,311.714,1; 495.59000000000003,312.015,1; 495.59000000000003,312.31600000000003,1; 495.59000000000003,312.61699999999996,1; 495.59000000000003,312.918,1; 495.59000000000003,313.219,1; 495.59000000000003,313.52,1; 495.59000000000003,313.821,1; 495.59000000000003,314.122,1; 495.59000000000003,314.423,1; 495.59000000000003,315.025,1; 495.59000000000003,315.326,1; 495.59000000000003,315.627,1; 495.59000000000003,315.928,1; 495.59000000000003,316.22900000000004,1; 495.59000000000003,316.831,1; 495.59000000000003,317.132,1; 495.59000000000003,317.433,1; 495.59000000000003,317.73400000000004,1; 495.59000000000003,318.03499999999997,1; 495.59000000000003,318.336,1; 495.59000000000003,318.637,1; 495.59000000000003,318.938,1; 495.59000000000003,319.23900000000003,1; 495.59000000000003,319.53999999999996,1; 495.59000000000003,319.841,1; 495.59000000000003,320.443,1; 495.59000000000003,320.744,1; 495.289,320.744,1; 495.289,321.04499999999996,1; 494.988,321.346,1; 494.988,321.647,1; 494.687,321.948,1; 494.687,322.249,1; 494.687,322.55,1; 494.687,322.851,1; 494.38599999999997,323.152,1; 494.38599999999997,323.453,1; 494.08500000000004,323.754,1; 494.08500000000004,324.055,1; 493.784,324.356,1; 494.08500000000004,324.356,1; 493.784,324.65700000000004,1; 493.483,324.95799999999997,1; 493.483,325.259,1; 493.182,325.56,1; 493.182,325.861,1; 492.881,326.16200000000003,1; 492.881,326.46299999999997,1; 492.58000000000004,326.46299999999997,1; 492.58000000000004,326.764,1; 492.58000000000004,327.065,1; 492.58000000000004,327.366,1; 492.279,327.366,1; 492.279,327.66700000000003,1; 492.279,327.96799999999996,1; 492.279,328.269,1; 492.279,328.57,1; 491.978,328.57,1; 491.978,328.871,1; 491.978,329.172,1; 491.677,329.172,1; 491.677,329.473,1; 491.677,329.774,1; 491.677,330.075,1; 491.677,330.376,1; 491.677,330.677,1; 491.376,330.978,1; 491.376,331.279,1; 491.376,331.58000000000004,1; 491.376,331.881,1; 491.376,332.483,1; 491.075,332.784,1; 491.075,333.08500000000004,1; 491.075,333.38599999999997,1; 491.075,333.988,1; 491.075,334.289,1; 491.075,334.59000000000003,1; 491.075,334.89099999999996,1; 491.075,335.192,1; 491.075,335.493,1; 491.075,335.794,1; 491.075,336.095,1; 491.075,336.39599999999996,1; 491.075,336.697,1; 491.075,336.998,1; 491.075,337.299,1; 491.075,337.6,1; 491.075,337.901,1; 491.075,338.202,1; 491.075,338.503,1; 491.075,338.804,1; 491.075,339.406,1; 491.075,339.707,1; 491.075,340.00800000000004,1; 491.075,340.61,1; 491.075,340.911,1; 491.075,341.51300000000003,1; 491.075,341.81399999999996,1; 491.075,342.416,1; 491.075,342.717,1; 491.075,343.01800000000003,1; 491.075,343.31899999999996,1; 491.075,343.62,1; 491.075,343.921,1; 491.075,344.222,1; 491.075,344.523,1; 491.075,344.824,1; 491.075,345.125,1; 491.075,345.426,1; 491.075,345.727,1; 490.774,346.028,1; 490.774,346.329,1; 490.774,346.63,1; 490.774,346.93100000000004,1; 490.473,346.93100000000004,1; 490.473,347.23199999999997,1; 490.473,347.533,1; 490.473,347.834,1; 490.473,348.135,1; 490.172,348.135,1; 490.172,348.43600000000004,1; 490.172,348.73699999999997,1; 490.172,349.038,1; 489.871,349.339,1; 489.871,349.64,1; 489.871,349.94100000000003,1; 489.871,350.24199999999996,1; 489.57,350.543,1; 489.57,350.844,1; 489.57,351.145,1; 489.57,351.446,1; 489.269,351.446,1; 489.269,351.747,1; 489.269,352.048,1; 488.96799999999996,352.349,1; 488.96799999999996,352.65,1; 488.96799999999996,352.951,1; 488.96799999999996,353.252,1; 488.66700000000003,353.553,1; 488.66700000000003,353.85400000000004,1; 488.66700000000003,354.155,1; 488.66700000000003,354.456,1; 488.66700000000003,354.757,1; 488.366,354.757,1; 488.366,355.058,1; 488.366,355.35900000000004,1; 488.366,355.65999999999997,1; 488.366,355.961,1; 488.366,356.262,1; 488.366,356.563,1; 488.366,356.86400000000003,1; 488.065,357.16499999999996,1; 488.065,357.466,1; 488.065,357.767,1; 488.065,358.068,1; 488.065,358.369,1; 488.065,358.66999999999996,1; 487.764,358.971,1; 487.764,359.272,1; 488.065,359.573,1; 487.764,359.874,1; 487.764,360.175,1; 487.764,360.777,1; 487.764,361.078,1; 487.764,361.379,1; 487.764,361.68,1; 487.764,361.981,1; 487.764,362.28200000000004,1; 487.764,362.58299999999997,1; 487.764,362.884,1; 487.764,363.185,1; 487.764,363.486,1; 487.764,363.78700000000003,1; 487.764,364.08799999999997,1; 487.764,364.389,1; 487.764,364.69,1; 487.764,364.991,1; 487.764,365.29200000000003,1; 487.764,365.59299999999996,1; 487.764,365.894,1; 487.764,366.195,1; 487.764,366.496,1; 487.764,366.797,1; 487.764,367.098,1; 487.764,367.399,1; 487.764,367.7,1; 487.46299999999997,368.001,1; 487.46299999999997,368.302,1; 487.46299999999997,368.603,1; 487.46299999999997,368.904,1; 487.16200000000003,368.904,1; 487.16200000000003,369.20500000000004,1; 487.16200000000003,369.506,1; 486.861,369.807,1; 486.861,370.108,1; 486.56,370.409,1; 486.259,370.71000000000004,1; 486.259,371.01099999999997,1; 485.95799999999997,371.312,1; 485.95799999999997,371.613,1; 485.95799999999997,371.914,1; 485.95799999999997,372.21500000000003,1; 485.95799999999997,372.51599999999996,1; 485.95799999999997,372.817,1; 485.65700000000004,372.817,1; 485.65700000000004,373.118,1; 485.65700000000004,373.419,1; 485.65700000000004,373.72,1; 485.356,374.02099999999996,1; 485.356,374.322,1; 485.356,374.623,1; 485.055,374.924,1; 485.055,375.225,1; 485.055,375.526,1; 485.055,375.827,1; 485.055,376.128,1; 485.055,376.429,1; 485.055,376.73,1; 485.055,377.031,1; 485.055,377.332,1; 485.055,377.63300000000004,1; 485.055,377.93399999999997,1; 485.055,378.235,1; 485.055,378.536,1; 485.055,378.837,1; 485.055,379.13800000000003,1; 485.055,379.43899999999996,1; 485.055,379.74,1; 485.055,380.041,1; 485.055,380.342,1; 485.055,380.64300000000003,1; 485.055,380.94399999999996,1; 485.055,381.245,1; 485.055,381.546,1; 485.055,381.847,1; 485.055,382.148,1; 485.055,382.449,1; 485.055,382.75,1; 484.754,382.75,1; 484.754,383.051,1; 484.754,383.352,1; 484.754,383.653,1; 484.453,383.653,1; 484.453,383.954,1; 484.152,384.255,1; 484.152,384.55600000000004,1; 483.851,384.85699999999997,1; 483.851,385.158,1; 483.851,385.459,1; 483.55,385.76,1; 483.55,386.06100000000004,1; 483.55,386.36199999999997,1; 483.55,386.663,1; 483.55,386.964,1; 483.55,387.265,1; 483.55,387.56600000000003,1; 483.249,387.56600000000003,1; 483.249,387.86699999999996,1; 483.249,388.168,1; 483.249,388.469,1; 483.249,388.77,1; 483.249,389.071,1; 483.249,389.372,1; 482.948,389.372,1; 482.948,389.673,1; 482.948,389.974,1; 482.948,390.275,1; 482.647,390.275,1; 482.647,390.576,1; 482.647,390.877,1; 482.647,391.178,1; 482.647,391.47900000000004,1; 482.647,391.78,1; 482.647,392.081,1; 482.647,392.382,1; 482.647,392.683,1; 482.647,392.98400000000004,1; 482.647,393.28499999999997,1; 482.647,393.586,1; 482.647,393.887,1; 482.647,394.188,1; 482.647,394.48900000000003,1; 482.647,394.78999999999996,1; 482.647,395.091,1; 482.647,395.392,1; 482.647,395.693,1; 482.647,395.994,1; 482.647,396.29499999999996,1; 482.647,396.596,1; 482.647,396.897,1; 482.647,397.198,1; 482.647,397.499,1; 482.647,397.8,1; 482.647,398.101,1; 482.647,397.8,1; 482.647,398.101,1; 482.647,398.402,1; 482.647,398.703,1; 482.647,399.004,1; 482.647,399.305,1; 482.647,399.606,1; 482.647,399.90700000000004,1; 482.346,399.90700000000004,1; 482.346,400.20799999999997,1; 482.346,400.509,1; 482.04499999999996,400.509,1; 482.04499999999996,400.81,1; 482.04499999999996,401.111,1; 481.744,401.111,1; 481.744,401.41200000000003,1; 481.443,401.41200000000003,1; 481.443,401.71299999999997,1; 481.142,401.71299999999997,1; 481.142,402.014,1; 481.142,401.71299999999997,1; 480.841,402.014,1; 480.841,402.315,1; 480.53999999999996,402.315,1; 480.53999999999996,402.616,1; 480.23900000000003,402.616,1; 479.938,402.616,1; 479.938,402.91700000000003,1; 479.637,402.91700000000003,1; 479.336,403.21799999999996,1; 479.03499999999997,403.519,1; 478.73400000000004,403.519,1; 478.73400000000004,403.82,1; 478.433,403.82,1; 478.132,403.82,1; 477.831,404.121,1; 477.53,404.121,1; 477.22900000000004,404.121,1; 477.22900000000004,404.422,1; 476.928,404.422,1; 476.627,404.422,1; 476.326,404.422,1; 476.025,404.422,1; 475.724,404.422,1; 475.423,404.422,1; 475.122,404.422,1; 474.821,404.422,1; 474.821,404.723,1; 474.52,404.723,1; 474.219,404.723,1; 473.918,404.723,1; 473.918,405.024,1; 473.61699999999996,405.024,1; 473.61699999999996,405.325,1; 473.31600000000003,405.325,1; 473.015,405.626,1; 472.714,405.626,1; 472.714,405.927,1; 472.413,405.927,1; 472.413,406.228,1; 472.11199999999997,406.228,1; 471.81100000000004,406.529,1; 471.51,406.529,1; 471.51,406.83000000000004,1; 471.209,406.83000000000004,1; 471.209,407.131,1; 470.908,407.432,1; 470.60699999999997,407.733,1; 470.30600000000004,408.034,1; 470.005,408.034,1; 470.005,408.33500000000004,1; 469.704,408.33500000000004,1; 469.704,408.63599999999997,1; 469.403,408.937,1; 469.102,408.937,1; 469.102,409.238,1; 468.801,409.238,1; 468.5,409.539,1; 468.199,409.539,1; 468.199,409.84000000000003,1; 467.898,409.84000000000003,1; 467.597,409.84000000000003,1; 467.597,410.14099999999996,1; 467.296,410.14099999999996,1; 466.995,410.14099999999996,1; 466.995,410.442,1; 466.69399999999996,410.442,1; 466.39300000000003,410.442,1; 466.092,410.442,1; 465.791,410.442,1; 465.49,410.442,1; 465.49,410.743,1; 465.49,410.442,1; 465.18899999999996,410.743,1; 464.88800000000003,410.743,1; 464.587,410.743,1; 464.587,411.044,1; 464.286,411.044,1; 463.985,411.044,1; 463.68399999999997,411.345,1; 463.38300000000004,411.345,1; 463.082,411.345,1; 462.781,411.345,1; 462.781,411.64599999999996,1; 462.48,411.345,1; 462.179,411.64599999999996,1; 461.878,411.64599999999996,1; 461.577,411.64599999999996,1; 461.276,411.64599999999996,1; 460.975,411.64599999999996,1; 460.674,411.64599999999996,1; 460.373,411.64599999999996,1; 460.072,411.64599999999996,1; 460.072,411.947,1; 459.77099999999996,411.947,1; 459.47,411.947,1; 459.169,411.947,1; 459.169,412.248,1; 458.868,412.248,1; 458.567,412.248,1; 458.567,412.549,1; 458.26599999999996,412.549,1; 457.96500000000003,412.549,1; 457.664,412.549,1; 457.363,412.549,1; 457.062,412.549,1; 456.76099999999997,412.549,1; 456.46000000000004,412.549,1; 456.159,412.549,1; 455.858,412.549,1; 455.858,412.248,1; 455.557,412.248,1; 455.557,411.947,1; 455.557,411.64599999999996,1; 455.557,411.345,1; 455.557,411.044,1; 455.256,410.743,1; 455.256,410.442,1; 455.256,410.14099999999996,1; 455.256,409.84000000000003,1; 455.256,409.539,1; 455.256,409.238,1; 455.256,408.937,1; 454.95500000000004,408.937,1; 454.95500000000004,408.63599999999997,1; 454.95500000000004,408.33500000000004,1; 454.95500000000004,408.034,1; 454.95500000000004,407.733,1; 454.95500000000004,407.432,1; 454.95500000000004,407.131,1; 454.95500000000004,406.83000000000004,1; 454.95500000000004,406.529,1; 454.95500000000004,406.228,1; 454.95500000000004,405.927,1; 454.95500000000004,405.626,1; 454.95500000000004,405.325,1; 454.95500000000004,405.024,1; 454.95500000000004,404.723,1; 454.95500000000004,404.422,1; 454.95500000000004,404.121,1; 454.95500000000004,403.82,1; 454.95500000000004,403.519,1; 454.95500000000004,403.21799999999996,1; 455.256,402.91700000000003,1; 454.95500000000004,402.91700000000003,1; 455.256,402.91700000000003,1; 455.256,402.616,1; 455.256,402.315,1; 455.256,402.014,1; 455.256,401.71299999999997,1; 455.256,401.41200000000003,1; 455.557,401.111,1; 455.557,400.81,1; 455.557,400.509,1; 455.557,400.20799999999997,1; 455.557,399.90700000000004,1; 455.858,399.606,1; 455.858,399.305,1; 455.858,399.004,1; 455.858,398.703,1; 456.159,398.703,1; 455.858,398.703,1; 456.159,398.703,1; 456.159,398.402,1; 456.159,398.101,1; 456.46000000000004,397.8,1; 456.46000000000004,397.499,1; 456.46000000000004,397.198,1; 456.46000000000004,396.897,1; 456.46000000000004,396.596,1; 456.76099999999997,396.596,1; 456.76099999999997,396.29499999999996,1; 456.76099999999997,395.994,1; 456.76099999999997,395.693,1; 456.76099999999997,395.392,1; 456.76099999999997,395.091,1; 456.76099999999997,394.78999999999996,1; 456.76099999999997,394.48900000000003,1; 456.76099999999997,394.188,1; 456.76099999999997,393.887,1; 456.76099999999997,393.586,1; 456.76099999999997,393.28499999999997,1; 456.76099999999997,392.98400000000004,1; 456.76099999999997,392.683,1; 456.76099999999997,392.98400000000004,1; 456.76099999999997,392.683,1; 456.76099999999997,392.382,1; 456.76099999999997,392.081,1; 456.76099999999997,391.78,1; 456.76099999999997,391.47900000000004,1; 456.76099999999997,391.178,1; 456.76099999999997,390.877,1; 456.46000000000004,390.576,1; 456.46000000000004,390.275,1; 456.159,389.974,1; 456.159,389.673,1; 455.858,389.372,1; 455.858,389.071,1; 455.858,388.77,1; 455.858,388.469,1; 455.557,388.168,1; 455.858,387.86699999999996,1; 455.557,387.86699999999996,1; 455.557,387.56600000000003,1; 455.557,387.265,1; 455.557,386.964,1; 455.557,386.663,1; 455.557,386.36199999999997,1; 455.557,386.06100000000004,1; 455.557,385.76,1; 455.557,385.459,1; 455.557,385.158,1; 455.557,384.85699999999997,1; 455.256,384.85699999999997,1; 455.256,384.55600000000004,1; 455.256,384.255,1; 455.256,383.954,1; 455.256,383.653,1; 455.256,383.352,1; 455.256,383.051,1; 455.256,382.75,1; 455.256,382.449,1; 455.256,382.148,1; 455.256,381.847,1; 455.256,381.546,1; 455.256,381.245,1; 455.256,380.94399999999996,1; 455.256,380.64300000000003,1; 455.256,380.342,1; 455.256,380.041,1; 455.256,379.74,1; 455.256,379.43899999999996,1; 455.256,379.13800000000003,1; 455.256,378.837,1; 455.256,378.536,1; 455.256,378.235,1; 455.256,377.93399999999997,1; 455.256,377.63300000000004,1; 455.256,377.332,1; 455.256,377.031,1; 455.256,376.73,1; 455.256,376.429,1; 455.256,376.128,1; 455.256,375.827,1; 455.256,375.526,1; 455.256,375.225,1; 455.256,374.924,1; 455.557,374.924,1; 455.557,374.623,1; 455.557,374.322,1; 455.557,374.02099999999996,1; 455.858,373.72,1; 455.858,373.419,1; 455.858,373.118,1; 456.159,372.817,1; 456.159,372.51599999999996,1; 456.159,372.21500000000003,1; 456.46000000000004,372.21500000000003,1; 456.46000000000004,371.914,1; 456.46000000000004,371.613,1; 456.76099999999997,371.613,1; 456.76099999999997,371.312,1; 456.76099999999997,371.01099999999997,1; 456.76099999999997,370.71000000000004,1; 457.062,370.71000000000004,1; 457.062,370.409,1; 457.062,370.108,1; 457.363,369.807,1; 457.363,369.506,1; 457.363,369.20500000000004,1; 457.664,368.904,1; 457.664,368.603,1; 457.664,368.302,1; 457.96500000000003,368.001,1; 457.96500000000003,367.7,1; 457.96500000000003,367.399,1; 457.96500000000003,367.098,1; 457.96500000000003,366.797,1; 457.96500000000003,366.496,1; 457.96500000000003,366.195,1; 458.26599999999996,366.195,1; 458.26599999999996,365.894,1; 457.96500000000003,365.894,1; 457.96500000000003,365.59299999999996,1; 458.26599999999996,365.59299999999996,1; 458.26599999999996,365.29200000000003,1; 458.26599999999996,364.991,1; 458.26599999999996,364.69,1; 458.26599999999996,364.389,1; 458.26599999999996,364.08799999999997,1; 458.26599999999996,363.78700000000003,1; 458.26599999999996,363.486,1; 458.26599999999996,363.185,1; 458.26599999999996,362.884,1; 458.26599999999996,362.58299999999997,1; 458.26599999999996,362.28200000000004,1; 458.26599999999996,361.981,1; 458.26599999999996,361.68,1; 458.26599999999996,361.379,1; 458.26599999999996,361.078,1; 458.26599999999996,360.777,1; 458.26599999999996,360.476,1; 458.26599999999996,360.175,1; 458.26599999999996,359.874,1; 458.26599999999996,359.573,1; 458.26599999999996,359.272,1; 458.26599999999996,358.971,1; 458.26599999999996,358.66999999999996,1; 458.26599999999996,358.369,1; 458.26599999999996,358.068,1; 458.26599999999996,357.767,1; 458.26599999999996,357.466,1; 458.26599999999996,357.16499999999996,1; 458.26599999999996,356.86400000000003,1; 458.26599999999996,356.563,1; 458.26599999999996,356.262,1; 458.26599999999996,355.961,1; 458.26599999999996,355.65999999999997,1; 458.26599999999996,355.35900000000004,1; 458.26599999999996,355.058,1; 458.26599999999996,354.757,1; 458.26599999999996,354.456,1; 458.26599999999996,354.155,1; 458.26599999999996,353.85400000000004,1; 458.26599999999996,353.553,1; 458.26599999999996,353.252,1; 458.26599999999996,352.951,1; 458.26599999999996,352.65,1; 458.26599999999996,352.349,1; 458.26599999999996,352.048,1; 458.26599999999996,351.747,1; 458.26599999999996,351.446,1; 458.26599999999996,351.145,1; 458.26599999999996,350.844,1; 458.26599999999996,350.543,1; 458.26599999999996,350.24199999999996,1; 458.26599999999996,349.94100000000003,1; 458.26599999999996,349.64,1; 458.26599999999996,349.339,1; 458.26599999999996,349.038,1; 458.26599999999996,348.73699999999997,1; 458.26599999999996,348.43600000000004,1; 458.26599999999996,348.135,1; 458.26599999999996,347.834,1; 457.96500000000003,347.834,1; 457.96500000000003,347.533,1; 457.96500000000003,347.834,1; 457.96500000000003,347.533,1; 457.96500000000003,347.23199999999997,1; 457.664,347.23199999999997,1; 457.96500000000003,347.23199999999997,1; 457.664,347.23199999999997,1; 457.363,347.23199999999997,1; 457.363,347.533,1; 457.363,347.834,1; 457.363,348.135,1; 457.363,348.43600000000004,1; 457.062,348.73699999999997,1; 457.062,349.038,1; 457.062,349.339,1; 457.062,349.64,1; 457.062,349.94100000000003,1; 457.062,350.24199999999996,1; 457.062,350.543,1; 456.76099999999997,350.844,1; 456.76099999999997,351.145,1; 457.062,351.145,1; 456.76099999999997,351.145,1; 456.76099999999997,351.446,1; 456.76099999999997,351.747,1; 456.76099999999997,352.048,1; 456.46000000000004,352.349,1; 456.46000000000004,352.65,1; 456.46000000000004,352.951,1; 456.159,353.252,1; 456.159,353.553,1; 456.159,353.85400000000004,1; 455.858,353.85400000000004,1; 455.858,354.155,1; 455.858,354.456,1; 455.858,354.757,1; 455.557,354.757,1; 455.557,355.058,1; 455.557,355.35900000000004,1; 455.557,355.65999999999997,1; 455.256,355.961,1; 455.256,356.262,1; 455.256,356.563,1; 454.95500000000004,356.563,1; 454.95500000000004,356.86400000000003,1; 454.95500000000004,357.16499999999996,1; 454.95500000000004,357.466,1; 454.95500000000004,357.767,1; 454.654,357.767,1; 454.654,358.068,1; 454.654,358.369,1; 454.353,358.66999999999996,1; 454.353,358.971,1; 454.353,359.272,1; 454.353,359.573,1; 454.052,359.573,1; 454.052,359.874,1; 454.052,360.175,1; 454.052,360.476,1; 453.751,360.777,1; 453.751,361.078,1; 453.751,361.379,1; 453.751,361.68,1; 453.45,361.68,1; 453.45,361.981,1; 453.751,361.981,1; 453.45,362.28200000000004,1; 453.45,362.58299999999997,1; 453.45,362.884,1; 453.45,363.185,1; 453.45,363.486,1; 453.45,363.78700000000003,1; 453.149,363.78700000000003,1; 453.149,364.08799999999997,1; 453.149,364.389,1; 453.149,364.69,1; 453.149,364.991,1; 453.149,365.29200000000003,1; 453.149,365.59299999999996,1; 453.149,365.894,1; 453.149,366.195,1; 452.848,366.195,1; 452.848,366.496,1; 452.848,366.797,1; 452.848,367.098,1; 452.848,367.399,1; 452.848,367.7,1; 452.848,368.001,1; 452.848,368.302,1; 452.848,368.603,1; 452.848,368.904,1; 452.848,369.20500000000004,1; 452.848,369.506,1; 452.848,369.807,1; 452.848,370.108,1; 452.848,370.409,1; 452.848,370.71000000000004,1; 452.547,370.71000000000004,1; 452.547,371.01099999999997,1; 452.547,371.312,1; 452.547,371.613,1; 452.547,371.914,1; 452.246,372.21500000000003,1; 452.246,372.51599999999996,1; 452.246,372.817,1; 451.945,372.817,1; 451.945,373.118,1; 451.945,373.419,1; 451.945,373.72,1; 451.644,373.72,1; 451.644,374.02099999999996,1; 451.644,374.322,1; 451.644,374.623,1; 451.34299999999996,374.924,1; 451.34299999999996,375.225,1; 451.04200000000003,375.526,1; 451.04200000000003,375.827,1; 451.04200000000003,376.128,1; 450.741,376.128,1; 450.741,376.429,1; 450.741,376.73,1; 450.741,377.031,1; 450.741,377.332,1; 450.44,377.332,1; 450.44,377.63300000000004,1; 450.44,377.93399999999997,1; 450.139,377.93399999999997,1; 450.139,378.235,1; 450.139,378.536,1; 449.83799999999997,378.837,1; 449.83799999999997,379.13800000000003,1; 449.83799999999997,379.43899999999996,1; 449.53700000000003,379.74,1; 449.53700000000003,380.041,1; 449.236,380.041,1; 449.236,380.342,1; 449.236,380.64300000000003,1; 448.935,380.64300000000003,1; 448.935,380.94399999999996,1; 448.634,381.245,1; 448.634,381.546,1; 448.634,381.847,1; 448.33299999999997,382.148,1; 448.33299999999997,382.449,1; 448.33299999999997,382.75,1; 448.03200000000004,382.75,1; 447.731,383.051,1; 447.731,383.352,1; 447.43,383.653,1; 447.43,383.954,1; 447.129,384.255,1; 447.129,384.55600000000004,1; 446.828,384.85699999999997,1; 446.828,385.158,1; 446.527,385.158,1; 446.527,385.459,1; 446.527,385.76,1; 446.226,385.76,1; 446.226,386.06100000000004,1; 446.226,386.36199999999997,1; 445.925,386.36199999999997,1; 445.925,386.663,1; 445.925,386.964,1; 445.624,387.265,1; 445.624,387.56600000000003,1; 445.323,387.56600000000003,1; 445.323,387.86699999999996,1; 445.323,388.168,1; 445.323,388.469,1; 445.022,388.469,1; 445.022,388.77,1; 445.022,389.071,1; 444.721,389.071,1; 444.721,389.372,1; 444.721,389.673,1; 444.721,389.974,1; 444.721,390.275,1; 444.721,390.576,1; 444.721,390.877,1; 444.42,390.877,1; 444.42,391.178,1; 444.42,391.47900000000004,1; 444.42,391.78,1; 444.42,392.081,1; 444.119,392.081,1; 444.42,392.081,1; 444.119,392.382,1; 444.119,392.683,1; 444.119,392.98400000000004,1; 443.818,392.98400000000004,1; 443.818,393.28499999999997,1; 444.119,393.28499999999997,1; 443.818,393.28499999999997,1; 444.119,393.28499999999997,1; 443.818,393.28499999999997,1; 443.818,393.586,1; 443.818,393.887,1; 443.818,394.188,1; 443.818,394.48900000000003,1; 443.818,394.78999999999996,1; 443.818,395.091,1; 443.818,395.392,1; 443.818,395.693,1; 443.818,395.994,1; 443.818,396.29499999999996,1; 443.818,396.596,1; 443.818,396.897,1; 443.818,397.198,1; 443.818,397.499,1; 444.119,397.8,1; 444.119,398.101,1; 444.42,398.101,1; 444.42,398.402,1; 444.42,398.703,1; 444.42,399.004,1; 444.42,399.305,1; 444.42,399.606,1; 444.42,399.90700000000004,1; 444.42,400.20799999999997,1; 444.42,400.509,1; 444.42,400.81,1; 444.42,401.111,1; 444.42,401.41200000000003,1; 444.42,401.71299999999997,1; 444.119,402.014,1; 444.119,402.315,1; 443.818,402.315,1; 443.818,402.616,1; 443.818,402.91700000000003,1; 443.517,402.91700000000003,1; 443.517,403.21799999999996,1; 443.216,403.519,1; 443.216,403.82,1; 442.915,403.82,1; 442.915,404.121,1; 442.61400000000003,404.121,1; 442.61400000000003,404.422,1; 442.61400000000003,404.723,1; 442.313,405.024,1; 442.012,405.325,1; 442.012,405.626,1; 441.711,405.927,1; 441.40999999999997,405.927,1; 441.40999999999997,406.228,1; 441.40999999999997,406.529,1; 441.109,406.83000000000004,1; 440.808,407.131,1; 440.808,407.432,1; 440.808,407.733,1; 440.507,407.733,1; 440.507,408.034,1; 440.507,408.33500000000004,1; 440.206,408.33500000000004,1; 440.206,408.63599999999997,1; 439.905,408.937,1; 439.905,409.238,1; 439.604,409.238,1; 439.604,409.539,1; 439.604,409.84000000000003,1; 439.303,409.84000000000003,1; 439.303,410.14099999999996,1; 439.002,410.442,1; 439.002,410.743,1; 439.002,411.044,1; 438.701,411.345,1; 438.701,411.64599999999996,1; 438.4,411.64599999999996,1; 438.4,411.947,1; 438.4,412.248,1; 438.099,412.549,1; 438.099,412.85,1; 437.798,413.151,1; 437.798,413.452,1; 437.497,413.753,1; 437.497,414.054,1; 437.196,414.054,1; 437.196,414.355,1; 437.196,414.656,1; 436.895,414.656,1; 436.895,414.957,1; 436.895,415.258,1; 436.594,415.258,1; 436.594,415.559,1; 436.594,415.86,1; 436.293,416.161,1; 435.992,416.462,1; 435.992,416.763,1; 435.69100000000003,417.064,1; 435.69100000000003,417.365,1; 435.69100000000003,417.666,1; 435.39,417.967,1; 435.39,418.268,1; 435.089,418.268,1; 435.089,418.569,1; 435.089,418.87,1; 434.788,419.171,1; 435.089,419.171,1; 434.788,419.171,1; 434.788,419.472,1; 434.788,419.773,1; 434.788,420.074,1; 434.48699999999997,420.375,1; 434.48699999999997,420.676,1; 434.48699999999997,420.977,1; 434.48699999999997,421.278,1; 434.18600000000004,421.278,1; 434.18600000000004,421.579,1; 434.18600000000004,421.88,1; 433.885,422.181,1; 433.885,422.482,1; 433.584,422.482,1; 433.584,422.783,1; 433.283,422.783,1; 433.283,423.084,1; 432.98199999999997,423.385,1; 432.98199999999997,423.686,1; 432.681,423.686,1; 432.681,423.987,1; 432.38,423.987,1; 432.38,424.288,1; 432.079,424.589,1; 431.778,424.89,1; 431.477,425.191,1; 431.176,425.492,1; 430.875,425.492,1; 430.875,425.793,1; 430.574,426.094,1; 430.574,426.395,1; 430.273,426.395,1; 430.273,426.696,1; 429.972,426.696,1; 429.972,426.997,1; 429.671,426.997,1; 429.37,427.298,1; 429.37,427.599,1; 429.069,427.599,1; 428.76800000000003,427.9,1; 428.467,428.201,1; 428.166,428.502,1; 427.865,428.803,1; 427.865,429.104,1; 427.56399999999996,429.104,1; 427.56399999999996,429.405,1; 427.26300000000003,429.405,1; 427.26300000000003,429.706,1; 426.962,430.007,1; 426.962,430.308,1; 426.661,430.308,1; 426.661,430.609,1; 426.36,430.609,1; 426.05899999999997,430.609,1; 426.05899999999997,430.91,1; 425.758,430.91,1; 425.758,431.211,1; 425.758,431.512,1; 425.457,431.512,1; 425.156,431.813,1; 424.855,432.114,1; 424.554,432.415,1; 424.253,432.415,1; 424.253,432.716,1; 423.952,432.716,1; 423.952,433.017,1; 423.651,433.017,1; 423.651,433.318,1; 423.35,433.619,1; 423.35,433.92,1; 423.35,434.221,1; 423.049,434.221,1; 423.049,434.522,1; 423.049,434.823,1; 423.049,435.124,1; 423.049,435.425,1; 423.049,435.726,1; 423.049,436.027,1; 423.049,436.328,1; 423.049,436.629,1; 423.049,436.93,1; 423.049,437.231,1; 423.049,437.532,1; 422.748,437.833,1; 422.748,438.134,1; 422.748,438.435,1; 422.447,438.435,1; 422.447,438.736,1; 422.447,439.037,1; 422.146,439.037,1; 422.146,439.338,1; 422.146,439.639,1; 421.845,439.639,1; 421.845,439.94,1; 421.544,439.94,1; 421.544,440.241,1; 421.243,440.542,1; 421.243,440.843,1; 420.942,440.843,1; 420.942,441.144,1; 420.641,441.445,1; 420.34000000000003,441.746,1; 420.039,442.047,1; 420.039,442.348,1; 419.738,442.348,1; 419.738,442.649,1; 419.437,442.649,1; 419.13599999999997,442.649,1; 419.13599999999997,442.95,1; 419.13599999999997,443.251,1; 418.835,443.251,1; 418.835,443.552,1; 418.534,443.552,1; 418.233,443.853,1; 418.233,444.154,1; 417.932,444.154,1; 417.932,444.455,1; 417.631,444.455,1; 417.631,444.756,1; 417.33,444.756,1; 417.029,445.057,1; 416.728,445.358,1; 416.427,445.659,1; 416.427,445.358,1; 416.427,445.659,1; 416.126,445.659,1; 415.825,445.659,1; 415.524,445.659,1; 415.223,445.659,1; 415.223,445.96,1; 414.922,445.96,1; 414.621,445.96,1; 414.32,445.96,1; 414.019,445.96,1; 413.718,445.96,1; 413.41700000000003,445.96,1; 413.116,445.96,1; 412.815,445.96,1; 412.514,445.96,1; 412.21299999999997,445.96,1; 412.21299999999997,446.261,1; 411.91200000000003,446.261,1; 411.611,446.261,1; 411.31,446.261,1; 411.009,446.261,1; 410.70799999999997,446.261,1; 410.407,446.562,1; 410.106,446.562,1; 410.106,446.863,1; 409.805,446.863,1; 409.504,447.164,1; 409.203,447.164,1; 409.203,447.465,1; 408.902,447.465,1; 408.601,447.465,1; 408.601,447.766,1; 408.3,448.067,1; 408.3,448.368,1; 407.999,448.368,1; 407.698,448.368,1; 407.698,448.669,1; 407.397,448.669,1; 407.397,448.97,1; 407.096,448.97,1; 407.096,449.271,1; 406.795,449.271,1; 406.494,449.271,1; 406.193,449.271,1; 405.892,449.271,1; 405.591,449.271,1; 405.29,449.271,1; 404.98900000000003,449.271,1; 404.688,449.271,1; 404.387,449.271,1; 404.086,449.271,1; 403.78499999999997,449.271,1; 403.484,449.271,1; 403.183,449.271,1; 402.882,449.271,1; 402.581,449.271,1; 402.28,449.271,1; 401.979,449.271,1; 401.979,448.97,1; 401.678,448.97,1; 401.678,448.669,1; 401.377,448.669,1; 401.076,448.669,1; 401.076,448.368,1; 400.775,448.368,1; 400.775,448.067,1; 400.474,448.067,1; 400.173,447.766,1; 399.872,447.465,1; 399.571,447.465,1; 399.571,447.164,1; 399.27,446.863,1; 399.27,446.562,1; 398.969,446.562,1; 398.969,446.261,1; 398.668,446.261,1; 398.367,446.261,1; 398.367,445.96,1; 398.06600000000003,445.96,1; 397.765,445.659,1; 397.464,445.659,1; 397.163,445.659,1; 396.86199999999997,445.358,1; 396.86199999999997,445.659,1; 396.56100000000004,445.358,1; 396.26,445.358,1; 396.26,445.057,1; 395.959,445.057,1; 395.658,445.057,1; 395.35699999999997,445.057,1; 395.056,445.057,1; 394.755,445.057,1; 394.454,445.057,1; 394.153,445.057,1; 394.153,444.756,1; 393.852,444.756,1; 393.551,444.756,1; 393.25,444.756,1; 392.949,444.756,1; 392.648,444.756,1; 392.347,444.756,1; 392.046,444.756,1; 392.046,444.455,1; 391.745,444.455,1; 391.745,444.154,1; 391.444,444.154,1; 391.444,443.853,1; 391.14300000000003,443.853,1; 391.14300000000003,443.552,1; 391.14300000000003,443.251,1; 391.14300000000003,442.95,1; 391.14300000000003,442.649,1; 391.14300000000003,442.348,1; 390.842,442.348,1; 390.842,442.047,1; 390.842,441.746,1; 390.842,441.445,1; 390.842,441.144,1; 390.842,440.843,1; 390.842,440.542,1; 390.842,440.241,1; 390.842,439.94,1; 390.842,439.639,1; 390.842,439.338,1; 390.842,439.037,1; 390.842,438.736,1; 390.842,438.435,1; 390.842,438.134,1; 390.842,437.833,1; 390.842,437.532,1; 390.842,437.231,1; 390.842,436.93,1; 390.842,436.629,1; 390.842,436.328,1; 390.842,436.027,1; 390.842,435.726,1; 390.842,435.425,1; 390.842,435.124,1; 390.842,434.823,1; 390.842,434.522,1; 390.842,434.221,1; 390.842,433.92,1; 390.842,433.619,1; 390.842,433.318,1; 390.842,433.017,1; 390.842,432.716,1; 390.842,432.415,1; 390.842,432.114,1; 390.842,431.813,1; 390.842,431.512,1; 390.842,431.211,1; 390.842,430.91,1; 391.14300000000003,430.91,1; 391.14300000000003,430.609,1; 391.14300000000003,430.308,1; 391.14300000000003,430.007,1; 391.14300000000003,429.706,1; 391.444,429.706,1; 391.444,429.405,1; 391.745,429.104,1; 391.745,428.803,1; 392.046,428.803,1; 392.046,428.502,1; 392.046,428.201,1; 392.347,428.201,1; 392.347,427.9,1; 392.347,427.599,1; 392.648,427.599,1; 392.648,427.298,1; 392.949,426.997,1; 392.949,426.696,1; 393.25,426.696,1; 393.25,426.395,1; 393.551,426.094,1; 393.551,425.793,1; 393.551,425.492,1; 393.852,425.492,1; 393.852,425.191,1; 394.153,424.89,1; 394.153,424.589,1; 394.454,424.589,1; 394.454,424.288,1; 394.454,423.987,1; 394.755,423.686,1; 394.755,423.385,1; 395.056,423.084,1; 395.056,422.783,1; 395.056,422.482,1; 395.35699999999997,422.482,1; 395.35699999999997,422.181,1; 395.35699999999997,421.88,1; 395.658,421.579,1; 395.658,421.278,1; 395.658,420.977,1; 395.959,420.676,1; 395.959,420.375,1; 395.959,420.074,1; 395.959,419.773,1; 396.26,419.773,1; 396.26,419.472,1; 396.56100000000004,419.171,1; 396.56100000000004,418.87,1; 396.56100000000004,418.569,1; 396.86199999999997,418.569,1; 396.86199999999997,418.268,1; 397.163,417.967,1; 397.163,417.666,1; 397.464,417.666,1; 397.464,417.365,1; 397.765,417.365,1; 397.765,417.064,1; 398.06600000000003,416.763,1; 398.06600000000003,416.462,1; 398.367,416.462,1; 398.367,416.161,1; 398.367,415.86,1; 398.367,415.559,1; 398.668,415.559,1; 398.668,415.258,1; 398.668,414.957,1; 398.668,414.656,1; 398.668,414.355,1; 398.668,414.054,1; 398.969,414.054,1; 398.969,413.753,1; 398.969,413.452,1; 398.969,413.151,1; 398.969,412.85,1; 398.969,412.549,1; 398.969,412.248,1; 398.969,411.947,1; 398.969,411.64599999999996,1; 398.969,411.345,1; 399.27,411.044,1; 399.27,410.743,1; 399.27,410.442,1; 399.27,410.14099999999996,1; 399.27,409.84000000000003,1; 399.27,409.539,1; 399.571,409.539,1; 399.571,409.238,1; 399.571,408.937,1; 399.872,408.63599999999997,1; 399.872,408.33500000000004,1; 399.872,408.034,1; 400.173,408.034,1; 400.173,407.733,1; 400.173,407.432,1; 400.474,407.131,1; 400.474,406.83000000000004,1; 400.775,406.83000000000004,1; 400.775,406.529,1; 400.775,406.228,1; 401.076,405.927,1; 401.076,405.626,1; 401.377,405.325,1; 401.377,405.024,1; 401.377,404.723,1; 401.678,404.422,1; 401.979,404.121,1; 401.979,403.82,1; 402.28,403.82,1; 402.28,403.519,1; 402.581,403.21799999999996,1; 402.581,402.91700000000003,1; 402.882,402.616,1; 402.882,402.315,1; 403.183,402.014,1; 403.183,401.71299999999997,1; 403.183,401.41200000000003,1; 403.484,401.41200000000003,1; 403.484,401.111,1; 403.78499999999997,401.111,1; 403.78499999999997,400.81,1; 404.086,400.81,1; 404.086,400.509,1; 404.387,400.20799999999997,1; 404.387,399.90700000000004,1; 404.688,399.90700000000004,1; 404.688,399.606,1; 404.98900000000003,399.305,1; 405.29,399.305,1; 405.29,399.004,1; 405.591,399.004,1; 405.591,398.703,1; 405.892,398.402,1; 405.892,398.101,1; 406.193,398.101,1; 406.193,397.8,1; 406.494,397.8,1; 406.494,397.499,1; 406.795,397.499,1; 406.795,397.198,1; 407.096,397.198,1; 407.096,396.897,1; 407.397,396.897,1; 407.397,396.596,1; 407.698,396.596,1; 407.698,396.29499999999996,1; 407.999,396.29499999999996,1; 408.3,396.29499999999996,1; 408.3,395.994,1; 408.601,395.994,1; 408.601,395.693,1; 408.902,395.693,1; 408.902,395.392,1; 409.203,395.392,1; 409.504,395.091,1; 409.805,395.091,1; 409.805,394.78999999999996,1; 410.106,394.78999999999996,1; 410.407,394.48900000000003,1; 410.70799999999997,394.188,1; 411.009,393.887,1; 411.31,393.586,1; 411.611,393.586,1; 411.611,393.28499999999997,1; 411.91200000000003,393.28499999999997,1; 411.91200000000003,392.98400000000004,1; 412.21299999999997,392.683,1; 412.514,392.683,1; 412.514,392.382,1; 412.815,392.382,1; 412.815,392.081,1; 413.116,392.081,1; 413.116,391.78,1; 413.41700000000003,391.78,1; 413.41700000000003,391.47900000000004,1; 413.718,391.47900000000004,1; 413.718,391.178,1; 414.019,391.178,1; 414.019,390.877,1; 414.32,390.576,1; 414.621,390.576,1; 414.621,390.275,1; 414.922,389.974,1; 414.922,389.673,1; 415.223,389.673,1; 415.223,389.372,1; 415.524,389.372,1; 415.524,389.071,1; 415.825,389.071,1; 415.825,388.77,1; 415.825,388.469,1; 416.126,388.469,1; 416.126,388.168,1; 416.427,388.168,1; 416.427,387.86699999999996,1; 416.728,387.86699999999996,1; 416.728,387.56600000000003,1; 417.029,387.56600000000003,1; 417.029,387.265,1; 417.33,387.265,1; 417.33,386.964,1; 417.631,386.964,1; 417.631,386.663,1; 417.932,386.36199999999997,1; 418.233,386.06100000000004,1; 418.233,385.76,1; 418.534,385.76,1; 418.534,385.459,1; 418.835,385.459,1; 418.835,385.158,1; 419.13599999999997,384.85699999999997,1; 419.437,384.85699999999997,1; 419.437,384.55600000000004,1; 419.437,384.255,1; 419.738,384.255,1; 420.039,383.954,1; 420.34000000000003,383.954,1; 420.34000000000003,383.653,1; 420.641,383.352,1; 420.641,383.051,1; 420.942,383.051,1; 420.942,382.75,1; 421.243,382.449,1; 421.544,382.148,1; 421.544,381.847,1; 421.845,381.847,1; 421.845,381.546,1; 422.146,381.245,1; 422.447,380.94399999999996,1; 422.447,380.64300000000003,1; 422.748,380.342,1; 422.748,380.041,1; 422.748,379.74,1; 423.049,379.74,1; 423.049,379.43899999999996,1; 423.35,379.13800000000003,1; 423.35,378.837,1; 423.35,378.536,1; 423.651,378.235,1; 423.651,377.93399999999997,1; 423.952,377.63300000000004,1; 423.952,377.332,1; 423.952,377.031,1; 424.253,376.73,1; 424.554,376.429,1; 424.554,376.128,1; 424.554,375.827,1; 424.554,375.526,1; 424.855,375.225,1; 424.855,374.924,1; 424.855,374.623,1; 425.156,374.623,1; 425.156,374.322,1; 425.156,374.02099999999996,1; 425.156,373.72,1; 425.457,373.419,1; 425.457,373.118,1; 425.457,372.817,1; 425.758,372.51599999999996,1; 425.758,372.21500000000003,1; 425.758,371.914,1; 425.758,371.613,1; 426.05899999999997,371.312,1; 426.05899999999997,371.01099999999997,1; 426.05899999999997,370.71000000000004,1; 426.05899999999997,370.409,1; 426.36,370.108,1; 426.36,369.807,1; 426.36,369.506,1; 426.661,369.20500000000004,1; 426.661,368.904,1; 426.661,368.603,1; 426.661,368.302,1; 426.962,368.302,1; 426.962,368.001,1; 426.962,367.7,1; 426.962,367.399,1; 426.962,367.098,1; 426.962,366.797,1; 426.962,366.496,1; 427.26300000000003,366.496,1; 427.26300000000003,366.195,1; 427.26300000000003,365.894,1; 427.26300000000003,365.59299999999996,1; 427.26300000000003,365.29200000000003,1; 427.26300000000003,364.991,1; 427.56399999999996,364.991,1; 427.56399999999996,364.69,1; 427.56399999999996,364.389,1; 427.56399999999996,364.08799999999997,1; 427.56399999999996,363.78700000000003,1; 427.56399999999996,363.486,1; 427.865,363.185,1; 427.865,362.884,1; 427.865,362.58299999999997,1; 427.865,362.28200000000004,1; 427.865,361.981,1; 427.865,361.68,1; 428.166,361.379,1; 427.865,361.078,1; 428.166,361.078,1; 428.166,360.777,1; 428.166,360.476,1; 428.166,360.175,1; 428.166,359.874,1; 428.166,359.573,1; 428.166,359.272,1; 428.467,359.272,1; 428.467,358.971,1; 428.467,358.66999999999996,1; 428.467,358.369,1; 428.467,358.068,1; 428.467,357.767,1; 428.467,357.466,1; 428.467,357.16499999999996,1; 428.76800000000003,357.16499999999996,1; 428.76800000000003,356.86400000000003,1; 428.76800000000003,356.563,1; 428.76800000000003,356.262,1; 428.76800000000003,355.961,1; 429.069,355.961,1; 429.069,355.65999999999997,1; 429.069,355.35900000000004,1; 429.069,355.058,1; 429.069,354.757,1; 429.37,354.456,1; 429.37,354.155,1; 429.37,353.85400000000004,1; 429.37,353.553,1; 429.37,353.252,1; 429.671,352.951,1; 429.671,352.65,1; 429.671,352.349,1; 429.671,352.048,1; 429.671,351.747,1; 429.671,351.446,1; 429.671,351.145,1; 429.671,350.844,1; 429.972,350.844,1; 429.972,350.543,1; 429.671,350.24199999999996,1; 429.972,350.24199999999996,1; 429.972,349.94100000000003,1; 429.972,349.64,1; 429.972,349.339,1; 429.972,349.038,1; 429.972,348.73699999999997,1; 429.972,348.43600000000004,1; 430.273,348.43600000000004,1; 430.273,348.135,1; 430.273,347.834,1; 430.273,347.533,1; 430.273,347.23199999999997,1; 430.273,346.93100000000004,1; 430.273,346.63,1; 430.273,346.329,1; 430.273,346.028,1; 430.273,345.727,1; 430.273,345.426,1; 430.273,345.125,1; 430.273,344.824,1; 430.273,344.523,1; 430.273,344.222,1; 430.273,343.921,1; 430.273,343.62,1; 430.273,343.31899999999996,1; 430.273,343.01800000000003,1; 430.273,342.717,1; 430.273,343.01800000000003,1; 430.273,342.717,1; 430.273,342.416,1; 430.273,342.115,1; 430.273,341.81399999999996,1; 430.273,341.51300000000003,1; 430.273,341.212,1; 430.273,340.911,1; 430.273,340.61,1; 430.273,340.911,1; 430.273,340.61,1; 430.273,340.30899999999997,1; 430.273,340.00800000000004,1; 430.273,339.707,1; 430.273,339.406,1; 430.273,339.105,1; 430.273,338.804,1; 430.273,338.503,1; 430.273,338.202,1; 430.273,337.901,1; 430.273,337.6,1; 429.972,337.299,1; 429.972,336.998,1; 429.671,336.697,1; 429.671,336.39599999999996,1; 429.37,336.095,1; 429.37,335.794,1; 429.069,335.493,1; 428.76800000000003,335.493,1; 428.76800000000003,335.192,1; 428.467,334.59000000000003,1; 428.166,334.59000000000003,1; 428.166,333.988,1; 427.865,333.988,1; 427.865,333.687,1; 427.865,333.38599999999997,1; 427.56399999999996,333.38599999999997,1; 427.56399999999996,333.08500000000004,1; 427.26300000000003,333.08500000000004,1; 427.26300000000003,332.784,1; 426.962,332.784,1; 426.962,332.483,1; 426.661,332.182,1; 426.661,331.881,1; 426.36,331.881,1; 426.05899999999997,331.58000000000004,1; 426.05899999999997,331.279,1; 426.05899999999997,330.978,1; 425.758,330.978,1; 425.758,330.677,1; 425.758,330.376,1; 425.758,330.075,1; 425.457,330.075,1; 425.457,329.774,1; 425.457,329.473,1; 425.156,329.172,1; 425.156,328.871,1; 425.156,328.57,1; 424.855,328.269,1; 424.554,327.96799999999996,1; 424.554,327.66700000000003,1; 424.554,327.366,1; 424.253,327.366,1; 424.253,327.065,1; 423.952,326.764,1; 423.952,326.46299999999997,1; 423.651,326.16200000000003,1; 423.651,325.861,1; 423.35,325.861,1; 423.35,325.56,1; 423.35,325.259,1; 423.049,325.259,1; 423.049,324.95799999999997,1; 422.748,324.65700000000004,1; 422.447,324.356,1; 422.447,324.055,1; 422.146,323.754,1; 422.146,323.453,1; 421.845,323.453,1; 421.845,323.152,1; 421.544,322.851,1; 421.544,322.55,1; 421.243,322.55,1; 421.243,322.249,1; 420.942,322.249,1; 420.942,321.948,1; 420.942,321.647,1; 420.641,321.647,1; 420.641,321.346,1; 420.641,321.647,1; 420.641,321.346,1; 420.34000000000003,321.346,1; 420.34000000000003,321.04499999999996,1; 420.34000000000003,320.744,1; 420.039,320.744,1; 420.039,320.443,1; 419.738,320.443,1; 419.738,320.142,1; 419.437,320.142,1; 419.437,319.841,1; 419.13599999999997,319.841,1; 419.13599999999997,319.53999999999996,1; 418.835,319.53999999999996,1; 418.835,319.23900000000003,1; 418.835,319.53999999999996,1; 418.835,319.23900000000003,1; 418.534,319.23900000000003,1; 418.534,318.938,1; 418.233,318.938,1; 417.932,318.637,1; 417.631,318.637,1; 417.33,318.637,1; 417.631,318.637,1; 417.33,318.637,1; 417.33,318.637,1; 417.029,318.637,1; 417.029,318.938,1; 416.728,319.23900000000003,1; 416.728,319.53999999999996,1; 416.728,319.841,1; 416.728,320.142,1; 416.728,320.443,1; 416.427,320.443,1; 416.427,320.744,1; 416.427,321.04499999999996,1; 416.126,321.346,1; 416.126,321.647,1; 416.126,321.948,1; 415.825,321.948,1; 415.825,322.249,1; 415.825,322.55,1; 415.825,322.851,1; 415.524,323.152,1; 415.524,323.453,1; 415.223,323.754,1; 415.223,324.055,1; 415.223,324.356,1; 415.223,324.65700000000004,1; 415.223,324.95799999999997,1; 415.223,325.259,1; 415.223,325.56,1; 414.922,325.861,1; 414.922,326.16200000000003,1; 414.922,326.46299999999997,1; 414.922,326.764,1; 414.922,327.065,1; 414.922,327.366,1; 414.922,327.66700000000003,1; 414.922,327.96799999999996,1; 414.922,328.269,1; 414.922,328.57,1; 414.922,328.871,1; 414.922,329.172,1; 414.922,329.473,1; 414.922,329.774,1; 414.922,330.075,1; 414.922,330.376,1; 414.922,330.677,1; 414.922,330.978,1; 414.922,331.279,1; 414.922,331.58000000000004,1; 414.922,331.881,1; 414.922,332.182,1; 414.922,332.483,1; 414.922,332.784,1; 414.922,333.08500000000004,1; 414.922,333.38599999999997,1; 414.922,333.687,1; 414.922,333.988,1; 414.922,334.289,1; 414.922,334.59000000000003,1; 414.922,334.89099999999996,1; 414.922,335.192,1; 414.922,335.493,1; 414.922,335.794,1; 414.922,336.095,1; 414.922,336.39599999999996,1; 414.922,336.697,1; 414.922,336.998,1; 414.922,337.299,1; 414.922,337.6,1; 414.922,337.901,1; 414.922,338.202,1; 414.922,338.503,1; 414.922,338.804,1; 414.922,339.105,1; 415.223,339.406,1; 415.223,339.707,1; 415.223,340.00800000000004,1; 415.223,340.30899999999997,1; 415.524,340.61,1; 415.524,340.911,1; 415.524,341.212,1; 415.524,341.51300000000003,1; 415.524,341.81399999999996,1; 415.825,342.115,1; 415.825,342.416,1; 415.825,342.717,1; 415.825,343.01800000000003,1; 415.825,343.31899999999996,1; 415.825,343.62,1; 416.126,343.921,1; 416.126,344.222,1; 416.126,344.523,1; 416.427,344.824,1; 416.427,345.125,1; 416.728,345.426,1; 416.728,345.727,1; 416.728,346.028,1; 417.029,346.329,1; 417.029,346.63,1; 417.33,346.63,1; 417.33,346.93100000000004,1; 417.631,347.23199999999997,1; 417.631,347.533,1; 417.932,347.533,1; 417.932,347.834,1; 418.233,347.834,1; 418.233,348.135,1; 418.534,348.43600000000004,1; 418.534,348.73699999999997,1; 418.835,348.73699999999997,1; 418.835,349.038,1; 419.13599999999997,349.339,1; 419.13599999999997,349.64,1; 419.437,349.64,1; 419.437,349.94100000000003,1; 419.437,350.24199999999996,1; 419.738,350.24199999999996,1; 419.738,350.543,1; 419.738,350.844,1; 420.039,350.844,1; 420.039,351.145,1; 420.039,351.446,1; 420.039,351.747,1; 420.039,352.048,1; 420.039,352.349,1; 420.34000000000003,352.65,1; 420.039,352.951,1; 420.34000000000003,352.951,1; 420.34000000000003,353.252,1; 420.34000000000003,353.553,1; 420.34000000000003,353.85400000000004,1; 420.34000000000003,354.155,1; 420.34000000000003,354.456,1; 420.34000000000003,354.757,1; 420.34000000000003,355.058,1; 420.34000000000003,355.35900000000004,1; 420.34000000000003,355.65999999999997,1; 420.34000000000003,355.961,1; 420.34000000000003,356.262,1; 420.34000000000003,356.563,1; 420.34000000000003,356.86400000000003,1; 420.34000000000003,357.16499999999996,1; 420.34000000000003,357.466,1; 420.34000000000003,357.767,1; 420.34000000000003,358.068,1; 420.34000000000003,358.369,1; 420.34000000000003,358.66999999999996,1; 420.34000000000003,358.971,1; 420.34000000000003,359.272,1; 420.34000000000003,359.573,1; 420.34000000000003,359.874,1; 420.34000000000003,360.175,1; 420.34000000000003,360.476,1; 420.34000000000003,360.777,1; 420.34000000000003,361.078,1; 420.34000000000003,361.379,1; 420.34000000000003,361.68,1; 420.34000000000003,361.981,1; 420.34000000000003,362.28200000000004,1; 420.34000000000003,362.58299999999997,1; 420.34000000000003,362.884,1; 420.34000000000003,363.185,1; 420.34000000000003,363.486,1; 420.34000000000003,363.78700000000003,1; 420.34000000000003,364.08799999999997,1; 420.34000000000003,364.389,1; 420.34000000000003,364.69,1; 420.34000000000003,364.991,1; 420.34000000000003,365.29200000000003,1; 420.34000000000003,365.59299999999996,1; 420.34000000000003,365.894,1; 420.34000000000003,366.195,1; 420.34000000000003,366.496,1; 420.34000000000003,366.797,1; 420.34000000000003,367.098,1; 420.34000000000003,367.399,1; 420.34000000000003,367.7,1; 420.34000000000003,368.001,1; 420.34000000000003,368.302,1; 420.34000000000003,368.603,1; 420.34000000000003,368.904,1; 420.34000000000003,369.20500000000004,1; 420.34000000000003,369.506,1; 420.34000000000003,369.807,1; 420.34000000000003,370.108,1; 420.34000000000003,370.409,1; 420.34000000000003,370.71000000000004,1; 420.34000000000003,371.01099999999997,1; 420.34000000000003,371.312,1; 420.34000000000003,371.613,1; 420.34000000000003,371.914,1; 420.34000000000003,372.21500000000003,1; 420.34000000000003,372.51599999999996,1; 420.34000000000003,372.817,1; 420.34000000000003,373.118,1; 420.34000000000003,373.419,1; 420.34000000000003,373.72,1; 420.34000000000003,374.02099999999996,1; 420.34000000000003,374.322,1; 420.34000000000003,374.623,1; 420.34000000000003,374.924,1; 420.34000000000003,375.225,1; 420.34000000000003,375.526,1; 420.34000000000003,375.827,1; 420.34000000000003,376.128,1; 420.34000000000003,376.429,1; 420.34000000000003,376.73,1; 420.34000000000003,377.031,1; 420.34000000000003,377.332,1; 420.34000000000003,377.63300000000004,1; 420.34000000000003,377.93399999999997,1; 420.34000000000003,378.235,1; 420.34000000000003,378.536,1; 420.34000000000003,378.837,1; 420.34000000000003,379.13800000000003,1; 420.34000000000003,379.43899999999996,1; 420.34000000000003,379.74,1; 420.34000000000003,380.041,1; 420.34000000000003,380.342,1; 420.34000000000003,380.64300000000003,1; 420.34000000000003,380.94399999999996,1; 420.34000000000003,381.245,1; 420.34000000000003,381.546,1; 420.34000000000003,381.847,1; 420.039,382.148,1; 420.039,382.449,1; 420.039,382.75,1; 420.039,383.051,1; 420.039,383.352,1; 419.738,383.352,1; 419.738,383.653,1; 419.738,383.352,1; 419.738,383.653,1; 419.738,383.954,1; 419.738,384.255,1; 419.437,384.255,1; 419.437,384.55600000000004,1; 419.437,384.85699999999997,1; 419.13599999999997,384.85699999999997,1; 419.13599999999997,385.158,1; 418.835,385.158,1; 418.835,385.459,1; 418.534,385.459,1; 418.534,385.76,1; 418.534,386.06100000000004,1; 418.233,386.06100000000004,1; 418.233,386.36199999999997,1; 417.932,386.36199999999997,1; 417.932,386.663,1; 417.631,386.663,1; 417.631,386.964,1; 417.33,387.265,1; 417.33,387.56600000000003,1; 417.029,387.56600000000003,1; 416.728,387.56600000000003,1; 416.728,387.86699999999996,1; 416.427,388.168,1; 416.126,388.469,1; 415.825,388.469,1; 415.825,388.77,1; 415.524,388.77,1; 415.524,389.071,1; 415.223,389.071,1; 414.922,389.071,1; 414.922,389.372,1; 414.621,389.372,1; 414.621,389.673,1; 414.32,389.673,1; 414.019,389.974,1; 413.718,389.974,1; 413.718,390.275,1; 413.41700000000003,390.576,1; 413.116,390.576,1; 413.116,390.877,1; 412.815,391.178,1; 412.514,391.178,1; 412.514,391.47900000000004,1; 412.21299999999997,391.78,1; 411.91200000000003,392.081,1; 411.611,392.382,1; 411.31,392.683,1; 411.31,392.98400000000004,1; 411.009,392.98400000000004,1; 411.009,393.28499999999997,1; 411.009,393.586,1; 410.70799999999997,393.586,1; 410.70799999999997,393.887,1; 410.407,393.887,1; 410.407,394.188,1; 410.407,394.48900000000003,1; 410.106,394.48900000000003,1; 410.106,394.78999999999996,1; 410.106,395.091,1; 409.805,395.392,1; 409.805,395.693,1; 409.504,395.994,1; 409.504,396.29499999999996,1; 409.504,396.596,1; 409.203,396.596,1; 409.203,396.897,1; 409.203,397.198,1; 409.203,397.499,1; 408.902,397.8,1; 408.902,398.101,1; 408.902,398.402,1; 408.601,398.402,1; 408.601,398.703,1; 408.601,399.004,1; 408.601,399.305,1; 408.3,399.305,1; 408.3,399.606,1; 408.3,399.90700000000004,1; 407.999,399.90700000000004,1; 407.999,400.20799999999997,1; 407.698,400.20799999999997,1; 407.397,400.20799999999997,1; 407.397,400.509,1; 407.096,400.509,1; 406.795,400.509,1; 406.494,400.509,1; 406.494,400.81,1; 406.193,400.81,1; 405.892,400.81,1; 405.892,401.111,1; 405.591,401.111,1; 405.29,401.41200000000003,1; 405.29,401.111,1; 405.29,401.41200000000003,1; 404.98900000000003,401.41200000000003,1; 404.688,401.71299999999997,1; 404.387,401.71299999999997,1; 404.086,401.71299999999997,1; 403.78499999999997,401.71299999999997,1; 403.484,402.014,1; 403.484,401.71299999999997,1; 403.183,401.71299999999997,1; 403.183,402.014,1; 402.882,402.014,1; 402.581,402.014,1; 402.28,402.014,1; 401.979,402.014,1; 401.979,401.71299999999997,1; 401.678,401.71299999999997,1; 401.678,401.41200000000003,1; 401.377,401.41200000000003,1; 401.377,401.111,1; 401.377,400.81,1; 401.076,400.81,1; 401.076,400.509,1; 401.076,400.20799999999997,1; 400.775,399.90700000000004,1; 400.775,399.606,1; 400.775,399.305,1; 400.775,399.004,1; 400.775,398.703,1; 400.775,398.402,1; 400.775,398.101,1; 400.775,397.8,1; 400.775,397.499,1; 400.775,397.198,1; 400.474,397.198,1; 400.474,396.897,1; 400.474,396.596,1; 400.474,396.29499999999996,1; 400.474,395.994,1; 400.474,395.693,1; 400.474,395.392,1; 400.474,395.091,1; 400.474,394.78999999999996,1; 400.474,394.48900000000003,1; 400.474,394.188,1; 400.474,393.887,1; 400.474,393.586,1; 400.474,393.28499999999997,1; 400.474,392.98400000000004,1; 400.474,392.683,1; 400.474,392.382,1; 400.474,392.081,1; 400.173,391.78,1; 400.173,391.47900000000004,1; 400.173,391.178,1; 400.173,390.877,1; 400.173,390.576,1; 400.173,390.275,1; 399.872,390.275,1; 399.872,389.974,1; 399.872,389.673,1; 399.571,389.673,1; 399.571,389.372,1; 399.571,389.071,1; 399.27,389.071,1; 399.27,388.77,1; 399.27,388.469,1; 398.969,388.168,1; 398.969,387.86699999999996,1; 398.969,387.56600000000003,1; 398.969,387.265,1; 398.969,386.964,1; 398.668,386.663,1; 398.668,386.36199999999997,1; 398.668,386.06100000000004,1; 398.668,385.76,1; 398.668,385.459,1; 398.668,385.158,1; 398.668,384.85699999999997,1; 398.668,384.55600000000004,1; 398.668,384.255,1; 398.668,383.954,1; 398.668,383.653,1; 398.668,383.352,1; 398.367,383.352,1; 398.367,383.051,1; 398.367,382.75,1; 398.367,382.449,1; 398.367,382.148,1; 398.367,381.847,1; 398.367,381.546,1; 398.367,381.245,1; 398.06600000000003,381.245,1; 398.06600000000003,380.94399999999996,1; 398.06600000000003,380.64300000000003,1; 398.06600000000003,380.342,1; 397.765,380.342,1; 397.765,380.041,1; 397.765,379.74,1; 397.765,379.43899999999996,1; 397.765,379.13800000000003,1; 397.464,378.837,1; 397.464,378.536,1; 397.163,377.93399999999997,1; 397.163,377.63300000000004,1; 396.86199999999997,377.332,1; 396.56100000000004,377.031,1; 396.56100000000004,376.429,1; 396.56100000000004,376.128,1; 396.26,375.827,1; 395.959,375.225,1; 395.959,374.924,1; 395.658,374.322,1; 395.658,374.02099999999996,1; 395.658,373.419,1; 395.35699999999997,373.118,1; 395.35699999999997,372.817,1; 395.35699999999997,372.51599999999996,1; 395.35699999999997,372.21500000000003,1; 395.056,371.914,1; 395.056,371.613,1; 395.056,371.312,1; 395.056,371.01099999999997,1; 394.755,371.01099999999997,1; 394.755,370.71000000000004,1; 394.755,370.409,1; 394.755,370.108,1; 394.755,369.807,1; 394.454,369.506,1; 394.454,369.20500000000004,1; 394.454,368.904,1; 394.454,368.603,1; 394.454,368.302,1; 394.153,368.001,1; 394.153,367.7,1; 394.153,367.399,1; 394.153,367.098,1; 393.852,366.797,1; 393.852,366.496,1; 393.551,366.195,1; 393.551,365.894,1; 393.551,365.59299999999996,1; 393.551,365.29200000000003,1; 393.551,364.991,1; 393.25,364.991,1; 393.25,364.69,1; 393.25,364.389,1; 393.25,364.08799999999997,1; 393.25,363.78700000000003,1; 392.949,363.78700000000003,1; 392.949,363.486,1; 392.949,363.185,1; 392.949,362.884,1; 392.949,362.58299999999997,1; 392.949,362.28200000000004,1; 392.648,361.981,1; 392.648,361.68,1; 392.648,361.379,1; 392.648,361.078,1; 392.347,361.078,1; 392.347,360.777,1; 392.347,360.476,1; 392.046,360.175,1; 392.046,359.874,1; 392.046,359.573,1; 391.745,359.272,1; 391.444,358.971,1; 391.444,358.66999999999996,1; 391.14300000000003,358.369,1; 391.14300000000003,358.068,1; 391.14300000000003,357.767,1; 390.842,357.466,1; 390.842,357.16499999999996,1; 390.541,356.86400000000003,1; 390.541,356.563,1; 390.541,356.262,1; 390.24,355.961,1; 390.24,355.65999999999997,1; 389.93899999999996,355.35900000000004,1; 389.93899999999996,355.058,1; 389.93899999999996,354.757,1; 389.63800000000003,354.456,1; 389.63800000000003,354.155,1; 389.337,353.85400000000004,1; 389.036,353.553,1; 389.036,353.252,1; 388.735,352.951,1; 388.735,352.65,1; 388.735,352.349,1; 388.43399999999997,352.048,1; 388.43399999999997,351.747,1; 388.133,351.747,1; 388.133,351.446,1; 388.133,351.145,1; 387.832,350.844,1; 387.832,350.543,1; 387.832,350.24199999999996,1; 387.832,349.94100000000003,1; 387.531,349.94100000000003,1; 387.531,349.64,1; 387.531,349.339,1; 387.531,349.038,1; 387.531,348.73699999999997,1; 387.531,348.43600000000004,1; 387.531,348.135,1; 387.531,347.834,1; 387.531,347.533,1; 387.23,347.533,1; 387.23,347.23199999999997,1; 387.23,346.93100000000004,1; 387.23,346.63,1; 387.23,346.329,1; 387.23,346.028,1; 387.23,345.727,1; 386.929,345.426,1; 386.929,345.125,1; 386.929,344.824,1; 386.929,344.523,1; 386.929,344.222,1; 386.929,343.921,1; 386.929,343.62,1; 386.929,343.31899999999996,1; 386.929,343.01800000000003,1; 386.929,342.717,1; 386.929,342.416,1; 386.929,342.115,1; 386.628,341.81399999999996,1; 386.628,341.51300000000003,1; 386.628,341.212,1; 386.628,340.911,1; 386.628,340.61,1; 386.327,340.30899999999997,1; 386.327,340.00800000000004,1; 386.327,339.707,1; 386.327,339.406,1; 386.327,339.105,1; 386.327,338.804,1; 386.327,338.503,1; 386.327,338.202,1; 386.327,337.901,1; 386.327,337.6,1; 386.327,337.299,1; 386.327,336.998,1; 386.327,336.697,1; 386.327,336.39599999999996,1; 386.327,336.095,1; 386.327,335.794,1; 386.327,335.493,1; 386.327,335.192,1; 386.327,334.89099999999996,1; 386.327,334.59000000000003,1; 386.327,334.289,1; 386.327,333.988,1; 386.327,333.687,1; 386.327,333.38599999999997,1; 386.327,333.08500000000004,1; 386.327,332.784,1; 386.327,332.483,1; 386.327,332.182,1; 386.327,331.881,1; 386.327,331.58000000000004,1; 386.026,331.279,1; 386.026,330.978,1; 386.026,330.677,1; 386.026,330.376,1; 385.725,330.075,1; 385.725,329.774,1; 385.725,329.172,1; 385.725,328.871,1; 385.424,328.871,1; 385.424,328.57,1; 385.424,328.269,1; 385.424,327.96799999999996,1; 385.123,327.66700000000003,1; 385.123,327.366,1; 385.123,327.065,1; 385.123,326.764,1; 385.123,326.46299999999997,1; 384.822,326.46299999999997,1; 384.822,326.16200000000003,1; 384.822,325.861,1; 384.822,325.56,1; 384.822,325.259,1; 384.521,325.259,1; 384.521,324.95799999999997,1; 384.521,324.65700000000004,1; 384.22,324.356,1; 384.22,324.055,1; 383.919,324.055,1; 383.919,323.754,1; 383.919,323.453,1; 383.919,323.152,1; 383.618,322.851,1; 383.618,322.55,1; 383.618,322.249,1; 383.317,321.948,1; 383.317,321.647,1; 383.016,321.346,1; 383.016,321.04499999999996,1; 383.016,320.744,1; 383.016,320.443,1; 383.016,320.142,1; 382.71500000000003,320.142,1; 382.71500000000003,319.841,1; 382.71500000000003,319.53999999999996,1; 382.71500000000003,319.23900000000003,1; 382.414,318.938,1; 382.414,318.637,1; 382.414,318.336,1; 382.414,318.03499999999997,1; 382.113,317.73400000000004,1; 382.113,317.433,1; 382.113,317.132,1; 381.812,316.831,1; 381.812,316.53,1; 381.812,316.22900000000004,1; 381.812,315.928,1; 381.812,315.627,1; 381.812,315.326,1; 381.511,315.326,1; 381.511,315.025,1; 381.511,314.724,1; 381.511,314.423,1; 381.511,314.122,1; 381.511,313.821,1; 381.21,313.52,1; 381.21,313.219,1; 381.21,312.918,1; 381.21,312.61699999999996,1; 381.21,312.31600000000003,1; 381.21,312.015,1; 381.21,311.714,1; 381.21,311.413,1; 381.21,311.11199999999997,1; 381.21,310.81100000000004,1; 381.21,310.51,1; 381.21,310.209,1; 381.21,309.908,1; 380.909,309.60699999999997,1; 381.21,309.60699999999997,1; 380.909,309.30600000000004,1; 380.909,309.005,1; 380.909,308.704,1; 380.909,308.403,1; 380.909,308.102,1; 380.909,307.801,1; 380.909,307.5,1; 380.909,307.199,1; 380.909,306.898,1; 380.608,306.597,1; 380.608,306.296,1; 380.608,305.995,1; 380.608,305.69399999999996,1; 380.307,305.39300000000003,1; 380.307,305.092,1; 380.307,304.791,1; 380.307,304.49,1; 380.307,304.18899999999996,1; 380.006,304.49,1; 380.307,304.18899999999996,1; 380.006,304.18899999999996,1; 379.705,304.18899999999996,1; 379.404,304.18899999999996,1; 379.103,304.18899999999996,1; 378.802,304.18899999999996,1; 378.501,304.18899999999996,1; 378.2,304.49,1; 377.899,304.791,1; 377.899,305.092,1; 377.598,305.39300000000003,1; 377.598,305.69399999999996,1; 377.598,305.995,1; 377.297,306.296,1; 377.297,306.597,1; 377.297,306.898,1; 377.297,307.199,1; 377.297,307.5,1; 376.996,307.5,1; 376.996,307.801,1; 376.996,308.102,1; 376.996,308.403,1; 376.695,308.403,1; 376.695,308.704,1; 376.695,309.005,1; 376.695,309.30600000000004,1; 376.394,309.30600000000004,1; 376.695,309.30600000000004,1; 376.394,309.30600000000004,1; 376.394,309.60699999999997,1; 376.093,309.60699999999997,1; 376.093,309.908,1; 376.093,310.209,1; 375.79200000000003,310.209,1; 375.79200000000003,310.51,1; 375.491,310.51,1; 375.491,310.81100000000004,1; 375.491,311.11199999999997,1; 375.19,311.413,1; 374.889,311.714,1; 374.889,312.015,1; 374.588,312.015,1; 374.588,312.31600000000003,1; 374.287,312.61699999999996,1; 374.287,312.918,1; 373.986,312.918,1; 373.986,313.219,1; 373.986,313.52,1; 373.685,313.821,1; 373.384,314.122,1; 373.08299999999997,314.122,1; 373.08299999999997,314.423,1; 373.08299999999997,314.724,1; 372.782,314.724,1; 372.782,315.025,1; 372.782,315.326,1; 372.481,315.326,1; 372.481,315.627,1; 372.18,315.627,1; 372.18,315.928,1; 371.879,315.928,1; 371.879,316.22900000000004,1; 371.879,316.53,1; 371.578,316.53,1; 371.578,316.831,1; 371.277,317.132,1; 370.976,317.433,1; 370.976,317.73400000000004,1; 370.675,317.73400000000004,1; 370.675,318.03499999999997,1; 370.374,318.03499999999997,1; 370.374,318.336,1; 370.073,318.637,1; 370.073,318.938,1; 369.772,318.938,1; 369.772,319.23900000000003,1; 369.471,319.53999999999996,1; 369.17,319.53999999999996,1; 369.17,319.841,1; 368.869,319.841,1; 368.869,320.142,1; 368.568,320.142,1; 368.267,320.142,1; 368.267,320.443,1; 367.966,320.443,1; 367.966,320.744,1; 367.665,320.744,1; 367.364,320.744,1; 367.063,320.744,1; 367.063,321.04499999999996,1; 366.762,321.04499999999996,1; 366.461,321.346,1; 366.15999999999997,321.346,1; 366.15999999999997,321.647,1; 365.859,321.647,1; 365.859,321.948,1; 365.558,322.249,1; 365.558,322.55,1; 365.257,322.55,1; 365.257,322.851,1; 364.956,322.851,1; 364.956,323.152,1; 364.655,323.152,1; 364.655,323.453,1; 364.354,323.453,1; 364.354,323.754,1; 364.354,324.055,1; 364.053,324.356,1; 363.752,324.65700000000004,1; 363.752,324.95799999999997,1; 363.451,325.259,1; 363.451,325.56,1; 363.15,325.861,1; 362.849,326.16200000000003,1; 362.548,326.46299999999997,1; 362.247,326.764,1; 362.247,327.065,1; 361.946,327.366,1; 361.946,327.66700000000003,1; 361.645,327.96799999999996,1; 361.645,328.269,1; 361.645,328.57,1; 361.344,328.57,1; 361.344,328.871,1; 361.043,328.871,1; 361.043,329.172,1; 361.043,329.473,1; 361.043,329.774,1; 360.742,329.774,1; 360.742,330.075,1; 360.44100000000003,330.376,1; 360.44100000000003,330.677,1; 360.14,330.677,1; 360.14,330.978,1; 359.839,330.978,1; 359.839,331.279,1; 359.538,331.279,1; 359.237,331.58000000000004,1; 359.237,331.881,1; 358.936,331.881,1; 358.936,332.182,1; 358.635,332.182,1; 358.334,332.483,1; 358.334,332.784,1; 358.033,332.784,1; 358.033,333.08500000000004,1; 357.73199999999997,333.08500000000004,1; 357.73199999999997,333.38599999999997,1; 357.431,333.38599999999997,1; 357.431,333.687,1; 357.13,333.988,1; 356.829,334.289,1; 356.528,334.289,1; 356.528,334.59000000000003,1; 356.227,334.59000000000003,1; 356.227,334.89099999999996,1; 355.926,334.89099999999996,1; 355.926,335.192,1; 355.625,335.493,1; 355.324,335.493,1; 355.324,335.794,1; 355.023,335.794,1; 355.023,336.095,1; 354.722,336.39599999999996,1; 354.421,336.697,1; 354.12,336.998,1; 353.819,336.998,1; 353.819,337.299,1; 353.51800000000003,337.299,1; 353.51800000000003,337.6,1; 353.217,337.6,1; 352.916,337.901,1; 352.615,337.901,1; 352.615,338.202,1; 352.314,338.202,1; 352.013,338.202,1; 351.712,338.503,1; 351.411,338.503,1; 351.11,338.503,1; 350.80899999999997,338.503,1; 350.508,338.503,1; 350.207,338.503,1; 349.906,338.503,1; 349.605,338.503,1; 349.304,338.503,1; 349.304,338.804,1; 349.003,338.804,1; 348.702,338.804,1; 348.401,338.804,1; 348.1,338.804,1; 347.799,338.804,1; 347.498,338.804,1; 347.197,338.804,1; 346.896,338.804,1; 346.595,338.804,1; 346.294,338.804,1; 345.993,338.804,1; 345.692,338.804,1; 345.391,338.804,1; 345.692,338.804,1; 345.391,338.804,1; 345.09,338.804,1; 344.789,338.804,1; 344.789,338.503,1; 344.488,338.503,1; 344.488,338.202,1; 344.187,338.202,1; 344.187,337.901,1; 343.886,337.901,1; 343.886,337.6,1; 343.585,337.6,1; 343.585,337.299,1; 343.284,336.998,1; 342.983,336.998,1; 342.983,336.697,1; 342.682,336.697,1; 342.682,336.39599999999996,1; 342.381,336.39599999999996,1; 342.08,336.095,1; 341.779,336.095,1; 341.478,335.794,1; 341.177,335.794,1; 341.177,335.493,1; 340.876,335.493,1; 340.575,335.192,1; 340.274,335.192,1; 339.973,334.89099999999996,1; 339.672,334.89099999999996,1; 339.973,334.89099999999996,1; 339.973,334.59000000000003,1; 339.672,334.59000000000003,1; 339.371,334.59000000000003,1; 339.371,334.289,1; 339.07,334.289,1; 339.07,333.988,1; 338.769,333.988,1; 338.468,333.687,1; 338.16700000000003,333.687,1; 337.866,333.687,1; 337.866,333.38599999999997,1; 337.565,333.38599999999997,1; 339.973,333.08500000000004,1; 339.672,333.38599999999997,1; 339.371,333.687,1; 339.07,333.988,1; 338.769,334.289,1; 338.468,334.59000000000003,1; 338.16700000000003,334.59000000000003,1; 338.16700000000003,334.89099999999996,1; 337.866,334.89099999999996,1; 337.565,334.89099999999996,1; 337.264,334.89099999999996,1; 336.963,334.89099999999996,1; 336.662,334.89099999999996,1; 336.361,334.89099999999996,1; 336.06,334.89099999999996,1; 335.759,334.89099999999996,1; 335.45799999999997,334.89099999999996,1; 335.157,334.89099999999996,1; 334.856,334.89099999999996,1; 334.555,334.89099999999996,1; 334.555,334.59000000000003,1; 334.254,334.59000000000003,1; 333.953,334.59000000000003,1; 333.652,334.59000000000003,1; 333.652,334.289,1; 333.351,334.289,1; 333.05,334.289,1; 333.05,333.988,1; 332.749,333.988,1; 332.749,333.687,1; 332.448,333.687,1; 332.448,333.38599999999997,1; 332.147,333.38599999999997,1; 332.147,333.08500000000004,1; 331.846,333.08500000000004,1; 331.846,332.784,1; 331.545,332.784,1; 331.545,332.483,1; 331.244,332.182,1; 331.244,331.881,1; 330.943,331.881,1; 330.943,331.58000000000004,1; 330.642,331.279,1; 330.642,330.978,1; 330.642,330.677,1; 330.642,330.376,1; 330.642,330.075,1; 330.642,329.774,1; 330.642,329.473,1; 330.642,329.172,1; 330.642,328.57,1; 330.642,326.46299999999997,1;</mask>
	</object>
</annotation>
